{
    "edges": [
        {
            "from": "just~title~_~0x59a3fe49",
            "id": "just~title~_~0x59a3fe49|once~title~_~0x59a3fe49",
            "label": "advmod",
            "title": "freq: 1",
            "to": "once~title~_~0x59a3fe49",
            "value": 1
        },
        {
            "from": "wheelie_bins~title~_~0x59a3fe49",
            "id": "wheelie_bins~title~_~0x59a3fe49|collect~title~_~0x59a3fe49",
            "label": "dobj",
            "title": "freq: 1",
            "to": "collect~title~_~0x59a3fe49",
            "value": 1
        },
        {
            "from": "once~title~_~0x59a3fe49",
            "id": "once~title~_~0x59a3fe49|collect~title~_~0x59a3fe49",
            "label": "advmod",
            "title": "freq: 1",
            "to": "collect~title~_~0x59a3fe49",
            "value": 1
        },
        {
            "from": "collect~title~_~0x59a3fe49",
            "id": "collect~title~_~0x59a3fe49|bury_council_votes~title~_~0x59a3fe49",
            "label": "xcomp",
            "title": "freq: 1",
            "to": "bury_council_votes~title~_~0x59a3fe49",
            "value": 1
        },
        {
            "from": "collect~title~_~0x59a3fe49",
            "id": "collect~title~_~0x59a3fe49|weeks~title~_~0x59a3fe49",
            "label": "nmod:tmod",
            "title": "freq: 1",
            "to": "weeks~title~_~0x59a3fe49",
            "value": 1
        }
    ],
    "nodes": [
        {
            "color": "lime",
            "id": "just~title~_~0x59a3fe49",
            "label": "just",
            "title": "*Freq: 1 <br> *Sen_Score: 0.0 <br> *Sentiment: {\"pos_count\": 0, \"neu_count\": 1, \"neg_count\": 0}",
            "value": 1
        },
        {
            "color": "lime",
            "id": "wheelie_bins~title~_~0x59a3fe49",
            "label": "wheelie_bins",
            "title": "*Freq: 1 <br> *Sen_Score: 0.0 <br> *Sentiment: {\"pos_count\": 0, \"neu_count\": 1, \"neg_count\": 0}",
            "value": 1
        },
        {
            "color": "lime",
            "id": "once~title~_~0x59a3fe49",
            "label": "once",
            "title": "*Freq: 1 <br> *Sen_Score: 0.0 <br> *Sentiment: {\"pos_count\": 0, \"neu_count\": 1, \"neg_count\": 0}",
            "value": 1
        },
        {
            "color": "lime",
            "id": "collect~title~_~0x59a3fe49",
            "label": "collect",
            "title": "*Freq: 1 <br> *Sen_Score: 0.0 <br> *Sentiment: {\"pos_count\": 0, \"neu_count\": 1, \"neg_count\": 0}",
            "value": 1
        },
        {
            "color": "lime",
            "id": "weeks~title~_~0x59a3fe49",
            "label": "weeks",
            "title": "*Freq: 1 <br> *Sen_Score: 0.0 <br> *Sentiment: {\"pos_count\": 0, \"neu_count\": 1, \"neg_count\": 0}",
            "value": 1
        },
        {
            "color": "lime",
            "id": "bury_council_votes~title~_~0x59a3fe49",
            "label": "bury_council_votes",
            "title": "*Freq: 1 <br> *Sen_Score: 0.0 <br> *Sentiment: {\"pos_count\": 0, \"neu_count\": 1, \"neg_count\": 0}",
            "value": 1
        }
    ],
    "options": {
        "build_option": {
            "build_mode": 0,
            "sentiment_ana_mode": "global"
        },
        "pruning_option": {
            "edge_freq_min": 1,
            "enable_pruning": true,
            "min_word_length": 2,
            "node_degree_min": 2,
            "node_freq_min": 1,
            "remove_isolated_node": true,
            "unify_matched_keywords": {
                "enable": true,
                "inter_cluster_unify": false,
                "intra_cluster_unify": true,
                "unification_mode": "contract"
            }
        },
        "timestamp": "2017-08-28 13:28:09 "
    }
}