{
    "edges": [
        {
            "from": "be~art.1~~0x59b6899c",
            "id": "be~art.1~~0x59b6899c|council~art.3~~0x59b689ae",
            "label": "nsubj",
            "title": "freq: 2",
            "to": "council~art.3~~0x59b689ae",
            "value": 2
        },
        {
            "from": "be~art.1~~0x59b6899c",
            "id": "be~art.1~~0x59b6899c|first~art.1~~0x59b68994",
            "label": "xcomp",
            "title": "freq: 2",
            "to": "first~art.1~~0x59b68994",
            "value": 2
        },
        {
            "from": "oppose~art.2~~0x59b6899f",
            "id": "oppose~art.2~~0x59b6899f|new_initiative~art.2~~0x59b6899f",
            "label": "dobj",
            "title": "freq: 2",
            "to": "new_initiative~art.2~~0x59b6899f",
            "value": 2
        },
        {
            "from": "tell~art.2~~0x59b689aa",
            "id": "tell~art.2~~0x59b689aa|wa~art.2~~0x59b689aa",
            "label": "auxpass",
            "title": "freq: 2",
            "to": "wa~art.2~~0x59b689aa",
            "value": 2
        },
        {
            "from": "tell~art.2~~0x59b689aa",
            "id": "tell~art.2~~0x59b689aa|town_hall~art.2~~0x59b689aa",
            "label": "nsubjpass",
            "title": "freq: 2",
            "to": "town_hall~art.2~~0x59b689aa",
            "value": 2
        },
        {
            "from": "tell~art.2~~0x59b689aa",
            "id": "tell~art.2~~0x59b689aa|make~art.0~~0x59b6898d",
            "label": "xcomp",
            "title": "freq: 2",
            "to": "make~art.0~~0x59b6898d",
            "value": 2
        },
        {
            "from": "empty~art.2~~0x59b689a6",
            "id": "empty~art.2~~0x59b689a6|bin~art.2~~0x59b689a1",
            "label": "nmod",
            "title": "freq: 2",
            "to": "bin~art.2~~0x59b689a1",
            "value": 2
        },
        {
            "from": "desperate_measure~art.2~~0x59b689aa",
            "id": "desperate_measure~art.2~~0x59b689aa|cost~art.0~~0x59b6898f",
            "label": "compound,compound",
            "title": "freq: 4",
            "to": "cost~art.0~~0x59b6898f",
            "value": 4
        },
        {
            "from": "desperate_measure~art.2~~0x59b689aa",
            "id": "desperate_measure~art.2~~0x59b689aa|be~art.1~~0x59b6899c",
            "label": "cop,cop",
            "title": "freq: 4",
            "to": "be~art.1~~0x59b6899c",
            "value": 4
        },
        {
            "from": "desperate_measure~art.2~~0x59b689aa",
            "id": "desperate_measure~art.2~~0x59b689aa|tell~art.2~~0x59b689aa",
            "label": "advcl",
            "title": "freq: 2",
            "to": "tell~art.2~~0x59b689aa",
            "value": 2
        },
        {
            "from": "desperate_measure~art.2~~0x59b689aa",
            "id": "desperate_measure~art.2~~0x59b689aa|save~art.2~~0x59b689a8",
            "label": "amod",
            "title": "freq: 2",
            "to": "save~art.2~~0x59b689a8",
            "value": 2
        },
        {
            "from": "desperate_measure~art.2~~0x59b689aa",
            "id": "desperate_measure~art.2~~0x59b689aa|cut~art.0~~0x59b6898f",
            "label": "compound",
            "title": "freq: 2",
            "to": "cut~art.0~~0x59b6898f",
            "value": 2
        },
        {
            "from": "accuse~art.1~~0x59b68999",
            "id": "accuse~art.1~~0x59b68999|warn~art.1~~0x59b68999",
            "label": "advcl",
            "title": "freq: 2",
            "to": "warn~art.1~~0x59b68999",
            "value": 2
        },
        {
            "from": "accuse~art.1~~0x59b68999",
            "id": "accuse~art.1~~0x59b68999|scaremongering~art.1~~0x59b68999",
            "label": "advcl",
            "title": "freq: 2",
            "to": "scaremongering~art.1~~0x59b68999",
            "value": 2
        },
        {
            "from": "responsibility~art.3~~0x59b689b3",
            "id": "responsibility~art.3~~0x59b689b3|waste_management~art.3~~0x59b689b3",
            "label": "nmod",
            "title": "freq: 2",
            "to": "waste_management~art.3~~0x59b689b3",
            "value": 2
        },
        {
            "from": "new_initiative~art.2~~0x59b6899f",
            "id": "new_initiative~art.2~~0x59b6899f|introduce~art.2~~0x59b6899f",
            "label": "acl:relcl",
            "title": "freq: 2",
            "to": "introduce~art.2~~0x59b6899f",
            "value": 2
        },
        {
            "from": "friendly_borough~art.0~~0x59b6898d",
            "id": "friendly_borough~art.0~~0x59b6898d|environmentally~art.0~~0x59b6898d",
            "label": "advmod",
            "title": "freq: 2",
            "to": "environmentally~art.0~~0x59b6898d",
            "value": 2
        },
        {
            "from": "councillor~art.1~~0x59b68999",
            "id": "councillor~art.1~~0x59b68999|vote~art.1~~0x59b68999",
            "label": "ccomp",
            "title": "freq: 2",
            "to": "vote~art.1~~0x59b68999",
            "value": 2
        },
        {
            "from": "councillor~art.1~~0x59b68999",
            "id": "councillor~art.1~~0x59b68999|opponent~art.1~~0x59b68999",
            "label": "ACCUSE",
            "title": "freq: 2",
            "to": "opponent~art.1~~0x59b68999",
            "value": 2
        },
        {
            "from": "councillor~art.1~~0x59b68999",
            "id": "councillor~art.1~~0x59b68999|bury~art.1~~0x59b68996",
            "label": "nmod",
            "title": "freq: 2",
            "to": "bury~art.1~~0x59b68996",
            "value": 2
        },
        {
            "from": "council~art.3~~0x59b689ae",
            "id": "council~art.3~~0x59b689ae|manchester~art.1~~0x59b68994",
            "label": "nmod",
            "title": "freq: 2",
            "to": "manchester~art.1~~0x59b68994",
            "value": 2
        },
        {
            "from": "waste_management~art.3~~0x59b689b3",
            "id": "waste_management~art.3~~0x59b689b3|lie~art.3~~0x59b689b3",
            "label": "acl",
            "title": "freq: 2",
            "to": "lie~art.3~~0x59b689b3",
            "value": 2
        },
        {
            "from": "bin~art.2~~0x59b689a1",
            "id": "bin~art.2~~0x59b689a1|colour~art.2~~0x59b689a4",
            "label": "amod",
            "title": "freq: 2",
            "to": "colour~art.2~~0x59b689a4",
            "value": 2
        },
        {
            "from": "bin~art.2~~0x59b689a1",
            "id": "bin~art.2~~0x59b689a1|communal~art.2~~0x59b689a6",
            "label": "amod",
            "title": "freq: 2",
            "to": "communal~art.2~~0x59b689a6",
            "value": 2
        },
        {
            "from": "bin~art.2~~0x59b689a1",
            "id": "bin~art.2~~0x59b689a1|wheelie~art.1~~0x59b68994",
            "label": "amod",
            "title": "freq: 2",
            "to": "wheelie~art.1~~0x59b68994",
            "value": 2
        },
        {
            "from": "bin~art.2~~0x59b689a1",
            "id": "bin~art.2~~0x59b689a1|used~art.2~~0x59b689a1",
            "label": "acl",
            "title": "freq: 2",
            "to": "used~art.2~~0x59b689a1",
            "value": 2
        },
        {
            "from": "bin~art.2~~0x59b689a1",
            "id": "bin~art.2~~0x59b689a1|grey~art.2~~0x59b689a1",
            "label": "amod",
            "title": "freq: 2",
            "to": "grey~art.2~~0x59b689a1",
            "value": 2
        },
        {
            "from": "bin~art.2~~0x59b689a1",
            "id": "bin~art.2~~0x59b689a1|serve~art.2~~0x59b689a6",
            "label": "acl",
            "title": "freq: 2",
            "to": "serve~art.2~~0x59b689a6",
            "value": 2
        },
        {
            "from": "bin~art.2~~0x59b689a1",
            "id": "bin~art.2~~0x59b689a1|paper~art.2~~0x59b689a4",
            "label": "nmod",
            "title": "freq: 2",
            "to": "paper~art.2~~0x59b689a4",
            "value": 2
        },
        {
            "from": "bin~art.2~~0x59b689a1",
            "id": "bin~art.2~~0x59b689a1|green~art.2~~0x59b689a4",
            "label": "amod",
            "title": "freq: 2",
            "to": "green~art.2~~0x59b689a4",
            "value": 2
        },
        {
            "from": "opponent~art.1~~0x59b68999",
            "id": "opponent~art.1~~0x59b68999|tip~art.1~~0x59b68996",
            "label": "amod",
            "title": "freq: 2",
            "to": "tip~art.1~~0x59b68996",
            "value": 2
        },
        {
            "from": "people~art.2~~0x59b6899f",
            "id": "people~art.2~~0x59b6899f|petition~art.2~~0x59b6899f",
            "label": "SIGN",
            "title": "freq: 2",
            "to": "petition~art.2~~0x59b6899f",
            "value": 2
        },
        {
            "from": "week~art.1~~0x59b68994",
            "id": "week~art.1~~0x59b68994|monthly~art.2~~0x59b689a4",
            "label": "nmod",
            "title": "freq: 2",
            "to": "monthly~art.2~~0x59b689a4",
            "value": 2
        },
        {
            "from": "warn~art.1~~0x59b68999",
            "id": "warn~art.1~~0x59b68999|pile~art.1~~0x59b68999",
            "label": "ccomp",
            "title": "freq: 2",
            "to": "pile~art.1~~0x59b68999",
            "value": 2
        },
        {
            "from": "fox~art.0~~0x59b6898d",
            "id": "fox~art.0~~0x59b6898d|vermin~art.0~~0x59b6898d",
            "label": "conj",
            "title": "freq: 2",
            "to": "vermin~art.0~~0x59b6898d",
            "value": 2
        },
        {
            "from": "part~art.2~~0x59b689a8",
            "id": "part~art.2~~0x59b689a8|strategy~art.2~~0x59b689a8",
            "label": "nmod",
            "title": "freq: 2",
            "to": "strategy~art.2~~0x59b689a8",
            "value": 2
        },
        {
            "from": "part~art.2~~0x59b689a8",
            "id": "part~art.2~~0x59b689a8|be~art.1~~0x59b6899c",
            "label": "cop",
            "title": "freq: 2",
            "to": "be~art.1~~0x59b6899c",
            "value": 2
        },
        {
            "from": "part~art.2~~0x59b689a8",
            "id": "part~art.2~~0x59b689a8|move~art.2~~0x59b689a8",
            "label": "nsubj",
            "title": "freq: 2",
            "to": "move~art.2~~0x59b689a8",
            "value": 2
        },
        {
            "from": "insist~art.0~~0x59b6898d",
            "id": "insist~art.0~~0x59b6898d|make~art.0~~0x59b6898d",
            "label": "ccomp",
            "title": "freq: 2",
            "to": "make~art.0~~0x59b6898d",
            "value": 2
        },
        {
            "from": "insist~art.0~~0x59b6898d",
            "id": "insist~art.0~~0x59b6898d|council~art.3~~0x59b689ae",
            "label": "nsubj",
            "title": "freq: 2",
            "to": "council~art.3~~0x59b689ae",
            "value": 2
        },
        {
            "from": "ivan_lewis~art.3~~0x59b689ae",
            "id": "ivan_lewis~art.3~~0x59b689ae|mp~art.3~~0x59b689b3",
            "label": "compound",
            "title": "freq: 2",
            "to": "mp~art.3~~0x59b689b3",
            "value": 2
        },
        {
            "from": "ivan_lewis~art.3~~0x59b689ae",
            "id": "ivan_lewis~art.3~~0x59b689ae|local~art.0~~0x59b6898d",
            "label": "amod",
            "title": "freq: 2",
            "to": "local~art.0~~0x59b6898d",
            "value": 2
        },
        {
            "from": "ivan_lewis~art.3~~0x59b689ae",
            "id": "ivan_lewis~art.3~~0x59b689ae|labour~art.3~~0x59b689ae",
            "label": "compound",
            "title": "freq: 2",
            "to": "labour~art.3~~0x59b689ae",
            "value": 2
        },
        {
            "from": "claim~art.2~~0x59b689a8",
            "id": "claim~art.2~~0x59b689a8|labour-run_council~art.2~~0x59b689a8",
            "label": "nsubj",
            "title": "freq: 2",
            "to": "labour-run_council~art.2~~0x59b689a8",
            "value": 2
        },
        {
            "from": "claim~art.2~~0x59b689a8",
            "id": "claim~art.2~~0x59b689a8|part~art.2~~0x59b689a8",
            "label": "ccomp",
            "title": "freq: 2",
            "to": "part~art.2~~0x59b689a8",
            "value": 2
        },
        {
            "from": "spend~art.1~~0x59b6899c",
            "id": "spend~art.1~~0x59b6899c|be~art.1~~0x59b6899c",
            "label": "auxpass",
            "title": "freq: 2",
            "to": "be~art.1~~0x59b6899c",
            "value": 2
        },
        {
            "from": "spend~art.1~~0x59b6899c",
            "id": "spend~art.1~~0x59b6899c|worker~art.1~~0x59b6899c",
            "label": "nmod",
            "title": "freq: 2",
            "to": "worker~art.1~~0x59b6899c",
            "value": 2
        },
        {
            "from": "decision~art.3~~0x59b689ae",
            "id": "decision~art.3~~0x59b689ae|difficult~art.3~~0x59b689ae",
            "label": "amod",
            "title": "freq: 2",
            "to": "difficult~art.3~~0x59b689ae",
            "value": 2
        },
        {
            "from": "coalition~art.3~~0x59b689ae",
            "id": "coalition~art.3~~0x59b689ae|effective_cut~art.3~~0x59b689ae",
            "label": "IMPOSE",
            "title": "freq: 2",
            "to": "effective_cut~art.3~~0x59b689ae",
            "value": 2
        },
        {
            "from": "year~art.4~~0x59b689b6",
            "id": "year~art.4~~0x59b689b6|next~art.2~~0x59b689aa",
            "label": "amod",
            "title": "freq: 2",
            "to": "next~art.2~~0x59b689aa",
            "value": 2
        },
        {
            "from": "bury~art.1~~0x59b68996",
            "id": "bury~art.1~~0x59b68996|boost~art.2~~0x59b689a8",
            "label": "conj",
            "title": "freq: 2",
            "to": "boost~art.2~~0x59b689a8",
            "value": 2
        },
        {
            "from": "bury~art.1~~0x59b68996",
            "id": "bury~art.1~~0x59b68996|save~art.2~~0x59b689a8",
            "label": "conj",
            "title": "freq: 2",
            "to": "save~art.2~~0x59b689a8",
            "value": 2
        },
        {
            "from": "bury~art.1~~0x59b68996",
            "id": "bury~art.1~~0x59b68996|waste_borough~art.2~~0x59b689a8",
            "label": "nmod",
            "title": "freq: 2",
            "to": "waste_borough~art.2~~0x59b689a8",
            "value": 2
        },
        {
            "from": "speak~art.4~~0x59b689b8",
            "id": "speak~art.4~~0x59b689b8|member~art.4~~0x59b689b8",
            "label": "nsubj",
            "title": "freq: 2",
            "to": "member~art.4~~0x59b689b8",
            "value": 2
        },
        {
            "from": "speak~art.4~~0x59b689b8",
            "id": "speak~art.4~~0x59b689b8|night~art.1~~0x59b68996",
            "label": "nmod:tmod",
            "title": "freq: 2",
            "to": "night~art.1~~0x59b68996",
            "value": 2
        },
        {
            "from": "speak~art.4~~0x59b689b8",
            "id": "speak~art.4~~0x59b689b8|wednesday~art.1~~0x59b68996",
            "label": "nmod",
            "title": "freq: 2",
            "to": "wednesday~art.1~~0x59b68996",
            "value": 2
        },
        {
            "from": "speak~art.4~~0x59b689b8",
            "id": "speak~art.4~~0x59b689b8|decision~art.3~~0x59b689ae",
            "label": "nmod",
            "title": "freq: 2",
            "to": "decision~art.3~~0x59b689ae",
            "value": 2
        },
        {
            "from": "speak~art.4~~0x59b689b8",
            "id": "speak~art.4~~0x59b689b8|meet~art.4~~0x59b689b8",
            "label": "nmod",
            "title": "freq: 2",
            "to": "meet~art.4~~0x59b689b8",
            "value": 2
        },
        {
            "from": "mean~art.3~~0x59b689b1",
            "id": "mean~art.3~~0x59b689b1|risk~art.3~~0x59b689b1",
            "label": "ccomp",
            "title": "freq: 2",
            "to": "risk~art.3~~0x59b689b1",
            "value": 2
        },
        {
            "from": "strategy~art.2~~0x59b689a8",
            "id": "strategy~art.2~~0x59b689a8|turn~art.2~~0x59b689a8",
            "label": "acl",
            "title": "freq: 2",
            "to": "turn~art.2~~0x59b689a8",
            "value": 2
        },
        {
            "from": "scrap~art.1~~0x59b68994",
            "id": "scrap~art.1~~0x59b68994|current_collection~art.1~~0x59b68994",
            "label": "dobj",
            "title": "freq: 2",
            "to": "current_collection~art.1~~0x59b68994",
            "value": 2
        },
        {
            "from": "lyndsay_warner~art.0~~0x59b68990",
            "id": "lyndsay_warner~art.0~~0x59b68990|controversial_decision~art.0~~0x59b68990",
            "label": "nmod",
            "title": "freq: 2",
            "to": "controversial_decision~art.0~~0x59b68990",
            "value": 2
        },
        {
            "from": "effective_cut~art.3~~0x59b689ae",
            "id": "effective_cut~art.3~~0x59b689ae|50_%~art.3~~0x59b689ae",
            "label": "amod",
            "title": "freq: 2",
            "to": "50_%~art.3~~0x59b689ae",
            "value": 2
        },
        {
            "from": "mp~art.3~~0x59b689b3",
            "id": "mp~art.3~~0x59b689b3|complaint~art.3~~0x59b689b3",
            "label": "RECEIVE",
            "title": "freq: 2",
            "to": "complaint~art.3~~0x59b689b3",
            "value": 2
        },
        {
            "from": "pass~art.1~~0x59b68996",
            "id": "pass~art.1~~0x59b68996|fear~art.0~~0x59b6898d",
            "label": "nmod",
            "title": "freq: 2",
            "to": "fear~art.0~~0x59b6898d",
            "value": 2
        },
        {
            "from": "pass~art.1~~0x59b68996",
            "id": "pass~art.1~~0x59b68996|unanimously~art.1~~0x59b68996",
            "label": "advmod",
            "title": "freq: 2",
            "to": "unanimously~art.1~~0x59b68996",
            "value": 2
        },
        {
            "from": "pass~art.1~~0x59b68996",
            "id": "pass~art.1~~0x59b68996|wednesday~art.1~~0x59b68996",
            "label": "nmod",
            "title": "freq: 2",
            "to": "wednesday~art.1~~0x59b68996",
            "value": 2
        },
        {
            "from": "pass~art.1~~0x59b68996",
            "id": "pass~art.1~~0x59b68996|night~art.1~~0x59b68996",
            "label": "nmod:tmod",
            "title": "freq: 2",
            "to": "night~art.1~~0x59b68996",
            "value": 2
        },
        {
            "from": "pass~art.1~~0x59b68996",
            "id": "pass~art.1~~0x59b68996|councillor~art.1~~0x59b68999",
            "label": "nmod",
            "title": "freq: 2",
            "to": "councillor~art.1~~0x59b68999",
            "value": 2
        },
        {
            "from": "pass~art.1~~0x59b68996",
            "id": "pass~art.1~~0x59b68996|wa~art.2~~0x59b689aa",
            "label": "auxpass",
            "title": "freq: 2",
            "to": "wa~art.2~~0x59b689aa",
            "value": 2
        },
        {
            "from": "pass~art.1~~0x59b68996",
            "id": "pass~art.1~~0x59b68996|controversial_decision~art.0~~0x59b68990",
            "label": "nsubjpass",
            "title": "freq: 2",
            "to": "controversial_decision~art.0~~0x59b68990",
            "value": 2
        },
        {
            "from": "impose~art.3~~0x59b689b1",
            "id": "impose~art.3~~0x59b689b1|have~art.3~~0x59b689ae",
            "label": "aux",
            "title": "freq: 2",
            "to": "have~art.3~~0x59b689ae",
            "value": 2
        },
        {
            "from": "impose~art.3~~0x59b689b1",
            "id": "impose~art.3~~0x59b689b1|be~art.1~~0x59b6899c",
            "label": "auxpass",
            "title": "freq: 2",
            "to": "be~art.1~~0x59b6899c",
            "value": 2
        },
        {
            "from": "impose~art.3~~0x59b689b1",
            "id": "impose~art.3~~0x59b689b1|budget~art.3~~0x59b689ae",
            "label": "nmod",
            "title": "freq: 2",
            "to": "budget~art.3~~0x59b689ae",
            "value": 2
        },
        {
            "from": "impose~art.3~~0x59b689b1",
            "id": "impose~art.3~~0x59b689b1|con/dem_government~art.3~~0x59b689b1",
            "label": "nmod",
            "title": "freq: 2",
            "to": "con/dem_government~art.3~~0x59b689b1",
            "value": 2
        },
        {
            "from": "general_waste~art.2~~0x59b689a1",
            "id": "general_waste~art.2~~0x59b689a1|recycle~art.2~~0x59b689a1",
            "label": "acl:relcl",
            "title": "freq: 2",
            "to": "recycle~art.2~~0x59b689a1",
            "value": 2
        },
        {
            "from": "general_waste~art.2~~0x59b689a1",
            "id": "general_waste~art.2~~0x59b689a1|household~art.2~~0x59b689a1",
            "label": "compound",
            "title": "freq: 2",
            "to": "household~art.2~~0x59b689a1",
            "value": 2
        },
        {
            "from": "falkirk~art.4~~0x59b689b6",
            "id": "falkirk~art.4~~0x59b689b6|scotland~art.4~~0x59b689b6",
            "label": "nmod",
            "title": "freq: 2",
            "to": "scotland~art.4~~0x59b689b6",
            "value": 2
        },
        {
            "from": "gwynedd_council~art.4~~0x59b689b6",
            "id": "gwynedd_council~art.4~~0x59b689b6|wale~art.4~~0x59b689b6",
            "label": "nmod",
            "title": "freq: 2",
            "to": "wale~art.4~~0x59b689b6",
            "value": 2
        },
        {
            "from": "worker~art.1~~0x59b6899c",
            "id": "worker~art.1~~0x59b6899c|social~art.1~~0x59b6899c",
            "label": "amod",
            "title": "freq: 2",
            "to": "social~art.1~~0x59b6899c",
            "value": 2
        },
        {
            "from": "complain~art.3~~0x59b689b3",
            "id": "complain~art.3~~0x59b689b3|mp~art.3~~0x59b689b3",
            "label": "nsubj",
            "title": "freq: 2",
            "to": "mp~art.3~~0x59b689b3",
            "value": 2
        },
        {
            "from": "complain~art.3~~0x59b689b3",
            "id": "complain~art.3~~0x59b689b3|receive~art.3~~0x59b689b3",
            "label": "ccomp",
            "title": "freq: 2",
            "to": "receive~art.3~~0x59b689b3",
            "value": 2
        },
        {
            "from": "turn~art.2~~0x59b689a8",
            "id": "turn~art.2~~0x59b689a8|bury~art.1~~0x59b68996",
            "label": "dep",
            "title": "freq: 2",
            "to": "bury~art.1~~0x59b68996",
            "value": 2
        },
        {
            "from": "attract~art.0~~0x59b6898d",
            "id": "attract~art.0~~0x59b6898d|vermin~art.0~~0x59b6898d",
            "label": "dobj",
            "title": "freq: 2",
            "to": "vermin~art.0~~0x59b6898d",
            "value": 2
        },
        {
            "from": "attract~art.0~~0x59b6898d",
            "id": "attract~art.0~~0x59b6898d|fox~art.0~~0x59b6898d",
            "label": "dobj",
            "title": "freq: 2",
            "to": "fox~art.0~~0x59b6898d",
            "value": 2
        },
        {
            "from": "lead~art.0~~0x59b6898d",
            "id": "lead~art.0~~0x59b6898d|falkirk~art.4~~0x59b689b6",
            "label": "nmod",
            "title": "freq: 2",
            "to": "falkirk~art.4~~0x59b689b6",
            "value": 2
        },
        {
            "from": "lead~art.0~~0x59b6898d",
            "id": "lead~art.0~~0x59b6898d|attract~art.0~~0x59b6898d",
            "label": "conj",
            "title": "freq: 2",
            "to": "attract~art.0~~0x59b6898d",
            "value": 2
        },
        {
            "from": "lead~art.0~~0x59b6898d",
            "id": "lead~art.0~~0x59b6898d|follow~art.4~~0x59b689b6",
            "label": "case",
            "title": "freq: 2",
            "to": "follow~art.4~~0x59b689b6",
            "value": 2
        },
        {
            "from": "lead~art.0~~0x59b6898d",
            "id": "lead~art.0~~0x59b6898d|new_move~art.0~~0x59b6898d",
            "label": "nsubj",
            "title": "freq: 2",
            "to": "new_move~art.0~~0x59b6898d",
            "value": 2
        },
        {
            "from": "lead~art.0~~0x59b6898d",
            "id": "lead~art.0~~0x59b6898d|increase~art.1~~0x59b68996",
            "label": "nmod",
            "title": "freq: 2",
            "to": "increase~art.1~~0x59b68996",
            "value": 2
        },
        {
            "from": "rubbish~art.4~~0x59b689b6",
            "id": "rubbish~art.4~~0x59b689b6|collect~art.1~~0x59b68994",
            "label": "amod",
            "title": "freq: 2",
            "to": "collect~art.1~~0x59b68994",
            "value": 2
        },
        {
            "from": "change~art.2~~0x59b689a6",
            "id": "change~art.2~~0x59b689a6|empty~art.2~~0x59b689a6",
            "label": "nsubj",
            "title": "freq: 2",
            "to": "empty~art.2~~0x59b689a6",
            "value": 2
        },
        {
            "from": "first~art.1~~0x59b68994",
            "id": "first~art.1~~0x59b68994|england~art.1~~0x59b68994",
            "label": "nmod",
            "title": "freq: 2",
            "to": "england~art.1~~0x59b68994",
            "value": 2
        },
        {
            "from": "first~art.1~~0x59b68994",
            "id": "first~art.1~~0x59b68994|be~art.1~~0x59b6899c",
            "label": "cop",
            "title": "freq: 2",
            "to": "be~art.1~~0x59b6899c",
            "value": 2
        },
        {
            "from": "first~art.1~~0x59b68994",
            "id": "first~art.1~~0x59b68994|start~art.1~~0x59b68994",
            "label": "acl",
            "title": "freq: 2",
            "to": "start~art.1~~0x59b68994",
            "value": 2
        },
        {
            "from": "recycle~art.2~~0x59b689a1",
            "id": "recycle~art.2~~0x59b689a1|be~art.1~~0x59b6899c",
            "label": "auxpass",
            "title": "freq: 2",
            "to": "be~art.1~~0x59b6899c",
            "value": 2
        },
        {
            "from": "risk~art.3~~0x59b689b1",
            "id": "risk~art.3~~0x59b689b1|be~art.1~~0x59b6899c",
            "label": "cop",
            "title": "freq: 2",
            "to": "be~art.1~~0x59b6899c",
            "value": 2
        },
        {
            "from": "risk~art.3~~0x59b689b1",
            "id": "risk~art.3~~0x59b689b1|line_service~art.3~~0x59b689b1",
            "label": "nsubj",
            "title": "freq: 2",
            "to": "line_service~art.3~~0x59b689b1",
            "value": 2
        },
        {
            "from": "save~art.2~~0x59b689a8",
            "id": "save~art.2~~0x59b689a8|landfill_fee~art.2~~0x59b689a8",
            "label": "nmod",
            "title": "freq: 2",
            "to": "landfill_fee~art.2~~0x59b689a8",
            "value": 2
        },
        {
            "from": "save~art.2~~0x59b689a8",
            "id": "save~art.2~~0x59b689a8|money~art.1~~0x59b6899c",
            "label": "dobj,nsubj",
            "title": "freq: 4",
            "to": "money~art.1~~0x59b6899c",
            "value": 4
        },
        {
            "from": "save~art.2~~0x59b689a8",
            "id": "save~art.2~~0x59b689a8|spend~art.1~~0x59b6899c",
            "label": "ccomp",
            "title": "freq: 2",
            "to": "spend~art.1~~0x59b6899c",
            "value": 2
        },
        {
            "from": "make~art.0~~0x59b6898d",
            "id": "make~art.0~~0x59b6898d|impose~art.3~~0x59b689b1",
            "label": "advcl",
            "title": "freq: 2",
            "to": "impose~art.3~~0x59b689b1",
            "value": 2
        },
        {
            "from": "make~art.0~~0x59b6898d",
            "id": "make~art.0~~0x59b6898d|be~art.1~~0x59b6899c",
            "label": "auxpass",
            "title": "freq: 2",
            "to": "be~art.1~~0x59b6899c",
            "value": 2
        },
        {
            "from": "lie~art.3~~0x59b689b3",
            "id": "lie~art.3~~0x59b689b3|local_government~art.3~~0x59b689b3",
            "label": "nmod",
            "title": "freq: 2",
            "to": "local_government~art.3~~0x59b689b3",
            "value": 2
        },
        {
            "from": "budget~art.3~~0x59b689ae",
            "id": "budget~art.3~~0x59b689ae|council~art.3~~0x59b689ae",
            "label": "nmod:poss",
            "title": "freq: 2",
            "to": "council~art.3~~0x59b689ae",
            "value": 2
        },
        {
            "from": "budget~art.3~~0x59b689ae",
            "id": "budget~art.3~~0x59b689ae|year~art.4~~0x59b689b6",
            "label": "nmod",
            "title": "freq: 2",
            "to": "year~art.4~~0x59b689b6",
            "value": 2
        },
        {
            "from": "paper~art.2~~0x59b689a4",
            "id": "paper~art.2~~0x59b689a4|plastic~art.2~~0x59b689a4",
            "label": "conj",
            "title": "freq: 2",
            "to": "plastic~art.2~~0x59b689a4",
            "value": 2
        },
        {
            "from": "paper~art.2~~0x59b689a4",
            "id": "paper~art.2~~0x59b689a4|glass~art.2~~0x59b689a4",
            "label": "conj",
            "title": "freq: 2",
            "to": "glass~art.2~~0x59b689a4",
            "value": 2
        },
        {
            "from": "start~art.1~~0x59b68994",
            "id": "start~art.1~~0x59b68994|rubbish~art.4~~0x59b689b6",
            "label": "dobj",
            "title": "freq: 2",
            "to": "rubbish~art.4~~0x59b689b6",
            "value": 2
        },
        {
            "from": "start~art.1~~0x59b68994",
            "id": "start~art.1~~0x59b68994|collect~art.1~~0x59b68994",
            "label": "xcomp",
            "title": "freq: 2",
            "to": "collect~art.1~~0x59b68994",
            "value": 2
        },
        {
            "from": "start~art.1~~0x59b68994",
            "id": "start~art.1~~0x59b68994|scrap~art.1~~0x59b68994",
            "label": "advcl",
            "title": "freq: 2",
            "to": "scrap~art.1~~0x59b68994",
            "value": 2
        },
        {
            "from": "start~art.1~~0x59b68994",
            "id": "start~art.1~~0x59b68994|week~art.1~~0x59b68994",
            "label": "nmod:tmod",
            "title": "freq: 2",
            "to": "week~art.1~~0x59b68994",
            "value": 2
        },
        {
            "from": "introduce~art.2~~0x59b6899f",
            "id": "introduce~art.2~~0x59b6899f|october~art.2~~0x59b6899f",
            "label": "nmod:tmod",
            "title": "freq: 2",
            "to": "october~art.2~~0x59b6899f",
            "value": 2
        },
        {
            "from": "introduce~art.2~~0x59b6899f",
            "id": "introduce~art.2~~0x59b6899f|be~art.1~~0x59b6899c",
            "label": "auxpass",
            "title": "freq: 2",
            "to": "be~art.1~~0x59b6899c",
            "value": 2
        },
        {
            "from": "unprecedented~art.3~~0x59b689b1",
            "id": "unprecedented~art.3~~0x59b689b1|be~art.1~~0x59b6899c",
            "label": "cop",
            "title": "freq: 2",
            "to": "be~art.1~~0x59b6899c",
            "value": 2
        },
        {
            "from": "unprecedented~art.3~~0x59b689b1",
            "id": "unprecedented~art.3~~0x59b689b1|cut~art.0~~0x59b6898f",
            "label": "nsubj",
            "title": "freq: 2",
            "to": "cut~art.0~~0x59b6898f",
            "value": 2
        },
        {
            "from": "unprecedented~art.3~~0x59b689b1",
            "id": "unprecedented~art.3~~0x59b689b1|mean~art.3~~0x59b689b1",
            "label": "conj",
            "title": "freq: 2",
            "to": "mean~art.3~~0x59b689b1",
            "value": 2
        },
        {
            "from": "member~art.4~~0x59b689b8",
            "id": "member~art.4~~0x59b689b8|public~art.4~~0x59b689b8",
            "label": "nmod",
            "title": "freq: 2",
            "to": "public~art.4~~0x59b689b8",
            "value": 2
        },
        {
            "from": "line_service~art.3~~0x59b689b1",
            "id": "line_service~art.3~~0x59b689b1|front~art.3~~0x59b689b1",
            "label": "amod",
            "title": "freq: 2",
            "to": "front~art.3~~0x59b689b1",
            "value": 2
        },
        {
            "from": "line_service~art.3~~0x59b689b1",
            "id": "line_service~art.3~~0x59b689b1|many~art.2~~0x59b689aa",
            "label": "amod",
            "title": "freq: 2",
            "to": "many~art.2~~0x59b689aa",
            "value": 2
        },
        {
            "from": "used~art.2~~0x59b689a1",
            "id": "used~art.2~~0x59b689a1|general_waste~art.2~~0x59b689a1",
            "label": "nmod",
            "title": "freq: 2",
            "to": "general_waste~art.2~~0x59b689a1",
            "value": 2
        },
        {
            "from": "receive~art.3~~0x59b689b3",
            "id": "receive~art.3~~0x59b689b3|other_issue~art.3~~0x59b689b3",
            "label": "nmod",
            "title": "freq: 2",
            "to": "other_issue~art.3~~0x59b689b3",
            "value": 2
        },
        {
            "from": "receive~art.3~~0x59b689b3",
            "id": "receive~art.3~~0x59b689b3|responsibility~art.3~~0x59b689b3",
            "label": "nmod",
            "title": "freq: 2",
            "to": "responsibility~art.3~~0x59b689b3",
            "value": 2
        },
        {
            "from": "local_government~art.3~~0x59b689b3",
            "id": "local_government~art.3~~0x59b689b3|parliament~art.3~~0x59b689b3",
            "label": "conj",
            "title": "freq: 2",
            "to": "parliament~art.3~~0x59b689b3",
            "value": 2
        },
        {
            "from": "say~art.3~~0x59b689b1",
            "id": "say~art.3~~0x59b689b1|ivan_lewis~art.3~~0x59b689ae",
            "label": "nsubj",
            "title": "freq: 2",
            "to": "ivan_lewis~art.3~~0x59b689ae",
            "value": 2
        },
        {
            "from": "say~art.3~~0x59b689b1",
            "id": "say~art.3~~0x59b689b1|have~art.3~~0x59b689ae",
            "label": "ccomp",
            "title": "freq: 2",
            "to": "have~art.3~~0x59b689ae",
            "value": 2
        },
        {
            "from": "say~art.3~~0x59b689b1",
            "id": "say~art.3~~0x59b689b1|blog~art.3~~0x59b689b1",
            "label": "nmod",
            "title": "freq: 2",
            "to": "blog~art.3~~0x59b689b1",
            "value": 2
        },
        {
            "from": "say~art.3~~0x59b689b1",
            "id": "say~art.3~~0x59b689b1|unprecedented~art.3~~0x59b689b1",
            "label": "ccomp",
            "title": "freq: 2",
            "to": "unprecedented~art.3~~0x59b689b1",
            "value": 2
        },
        {
            "from": "cut~art.0~~0x59b6898f",
            "id": "cut~art.0~~0x59b6898f|year~art.4~~0x59b689b6",
            "label": "nmod",
            "title": "freq: 2",
            "to": "year~art.4~~0x59b689b6",
            "value": 2
        },
        {
            "from": "cut~art.0~~0x59b6898f",
            "id": "cut~art.0~~0x59b6898f|impose~art.3~~0x59b689b1",
            "label": "acl",
            "title": "freq: 2",
            "to": "impose~art.3~~0x59b689b1",
            "value": 2
        },
        {
            "from": "green~art.2~~0x59b689a4",
            "id": "green~art.2~~0x59b689a4|blue~art.2~~0x59b689a4",
            "label": "conj",
            "title": "freq: 2",
            "to": "blue~art.2~~0x59b689a4",
            "value": 2
        },
        {
            "from": "pile~art.1~~0x59b68999",
            "id": "pile~art.1~~0x59b68999|rubbish~art.4~~0x59b689b6",
            "label": "nsubj",
            "title": "freq: 2",
            "to": "rubbish~art.4~~0x59b689b6",
            "value": 2
        },
        {
            "from": "pile~art.1~~0x59b68999",
            "id": "pile~art.1~~0x59b68999|attract~art.0~~0x59b6898d",
            "label": "conj",
            "title": "freq: 2",
            "to": "attract~art.0~~0x59b6898d",
            "value": 2
        },
        {
            "from": "increase~art.1~~0x59b68996",
            "id": "increase~art.1~~0x59b68996|tip~art.1~~0x59b68996",
            "label": "nsubj",
            "title": "freq: 2",
            "to": "tip~art.1~~0x59b68996",
            "value": 2
        },
        {
            "from": "increase~art.1~~0x59b68996",
            "id": "increase~art.1~~0x59b68996|fly-tipping~art.0~~0x59b6898d",
            "label": "nmod",
            "title": "freq: 2",
            "to": "fly-tipping~art.0~~0x59b6898d",
            "value": 2
        },
        {
            "from": "current_collection~art.1~~0x59b68994",
            "id": "current_collection~art.1~~0x59b68994|fortnightly~art.1~~0x59b68994",
            "label": "compound",
            "title": "freq: 2",
            "to": "fortnightly~art.1~~0x59b68994",
            "value": 2
        },
        {
            "from": "collect~art.1~~0x59b68994",
            "id": "collect~art.1~~0x59b68994|bin~art.2~~0x59b689a1",
            "label": "dobj,nsubjpass",
            "title": "freq: 4",
            "to": "bin~art.2~~0x59b689a1",
            "value": 4
        },
        {
            "from": "collect~art.1~~0x59b68994",
            "id": "collect~art.1~~0x59b68994|week~art.1~~0x59b68994",
            "label": "dobj",
            "title": "freq: 2",
            "to": "week~art.1~~0x59b68994",
            "value": 2
        },
        {
            "from": "collect~art.1~~0x59b68994",
            "id": "collect~art.1~~0x59b68994|be~art.1~~0x59b6899c",
            "label": "auxpass",
            "title": "freq: 2",
            "to": "be~art.1~~0x59b6899c",
            "value": 2
        },
        {
            "from": "complaint~art.3~~0x59b689b3",
            "id": "complaint~art.3~~0x59b689b3|bin_collection~art.3~~0x59b689b3",
            "label": "nmod",
            "title": "freq: 2",
            "to": "bin_collection~art.3~~0x59b689b3",
            "value": 2
        },
        {
            "from": "serve~art.2~~0x59b689a6",
            "id": "serve~art.2~~0x59b689a6|flat~art.2~~0x59b689a6",
            "label": "dobj",
            "title": "freq: 2",
            "to": "flat~art.2~~0x59b689a6",
            "value": 2
        },
        {
            "from": "argue~art.1~~0x59b6899c",
            "id": "argue~art.1~~0x59b6899c|save~art.2~~0x59b689a8",
            "label": "ccomp",
            "title": "freq: 2",
            "to": "save~art.2~~0x59b689a8",
            "value": 2
        },
        {
            "from": "have~art.3~~0x59b689ae",
            "id": "have~art.3~~0x59b689ae|make~art.0~~0x59b6898d",
            "label": "xcomp",
            "title": "freq: 2",
            "to": "make~art.0~~0x59b6898d",
            "value": 2
        },
        {
            "from": "have~art.3~~0x59b689ae",
            "id": "have~art.3~~0x59b689ae|decision~art.3~~0x59b689ae",
            "label": "nsubj",
            "title": "freq: 2",
            "to": "decision~art.3~~0x59b689ae",
            "value": 2
        },
        {
            "from": "boost~art.2~~0x59b689a8",
            "id": "boost~art.2~~0x59b689a8|recycle~art.2~~0x59b689a1",
            "label": "dobj",
            "title": "freq: 2",
            "to": "recycle~art.2~~0x59b689a1",
            "value": 2
        },
        {
            "from": "resident~art.2~~0x59b689aa",
            "id": "resident~art.2~~0x59b689aa|many~art.2~~0x59b689aa",
            "label": "amod",
            "title": "freq: 2",
            "to": "many~art.2~~0x59b689aa",
            "value": 2
        },
        {
            "from": "town_hall~art.2~~0x59b689aa",
            "id": "town_hall~art.2~~0x59b689aa|bury~art.1~~0x59b68996",
            "label": "compound",
            "title": "freq: 2",
            "to": "bury~art.1~~0x59b68996",
            "value": 2
        },
        {
            "from": "vote~art.1~~0x59b68999",
            "id": "vote~art.1~~0x59b68999|gwynedd_council~art.4~~0x59b689b6",
            "label": "nsubj",
            "title": "freq: 2",
            "to": "gwynedd_council~art.4~~0x59b689b6",
            "value": 2
        },
        {
            "from": "vote~art.1~~0x59b68999",
            "id": "vote~art.1~~0x59b68999|lead~art.0~~0x59b6898d",
            "label": "nmod",
            "title": "freq: 2",
            "to": "lead~art.0~~0x59b6898d",
            "value": 2
        },
        {
            "from": "vote~art.1~~0x59b68999",
            "id": "vote~art.1~~0x59b68999|year~art.4~~0x59b689b6",
            "label": "nmod:tmod",
            "title": "freq: 2",
            "to": "year~art.4~~0x59b689b6",
            "value": 2
        },
        {
            "from": "vote~art.1~~0x59b68999",
            "id": "vote~art.1~~0x59b68999|week~art.1~~0x59b68994",
            "label": "nmod:tmod",
            "title": "freq: 2",
            "to": "week~art.1~~0x59b68994",
            "value": 2
        },
        {
            "from": "vote~art.1~~0x59b68999",
            "id": "vote~art.1~~0x59b68999|motion~art.1~~0x59b68999",
            "label": "nmod",
            "title": "freq: 2",
            "to": "motion~art.1~~0x59b68999",
            "value": 2
        },
        {
            "from": "vote~art.1~~0x59b68999",
            "id": "vote~art.1~~0x59b68999|start~art.1~~0x59b68994",
            "label": "xcomp",
            "title": "freq: 2",
            "to": "start~art.1~~0x59b68994",
            "value": 2
        },
        {
            "from": "con/dem_government~art.3~~0x59b689b1",
            "id": "con/dem_government~art.3~~0x59b689b1|bury_council~art.3~~0x59b689b1",
            "label": "nmod",
            "title": "freq: 2",
            "to": "bury_council~art.3~~0x59b689b1",
            "value": 2
        },
        {
            "from": "fear~art.0~~0x59b6898d",
            "id": "fear~art.0~~0x59b6898d|insist~art.0~~0x59b6898d",
            "label": "conj",
            "title": "freq: 2",
            "to": "insist~art.0~~0x59b6898d",
            "value": 2
        },
        {
            "from": "fear~art.0~~0x59b6898d",
            "id": "fear~art.0~~0x59b6898d|local~art.0~~0x59b6898d",
            "label": "nsubj",
            "title": "freq: 2",
            "to": "local~art.0~~0x59b6898d",
            "value": 2
        },
        {
            "from": "fear~art.0~~0x59b6898d",
            "id": "fear~art.0~~0x59b6898d|lead~art.0~~0x59b6898d",
            "label": "ccomp",
            "title": "freq: 2",
            "to": "lead~art.0~~0x59b6898d",
            "value": 2
        },
        {
            "from": "fear~art.0~~0x59b6898d",
            "id": "fear~art.0~~0x59b6898d|fly~art.1~~0x59b68996",
            "label": "acl:relcl",
            "title": "freq: 2",
            "to": "fly~art.1~~0x59b68996",
            "value": 2
        },
        {
            "from": "fly~art.1~~0x59b68996",
            "id": "fly~art.1~~0x59b68996|increase~art.1~~0x59b68996",
            "label": "ccomp",
            "title": "freq: 2",
            "to": "increase~art.1~~0x59b68996",
            "value": 2
        },
        {
            "from": "feel~art.2~~0x59b689aa",
            "id": "feel~art.2~~0x59b689aa|resident~art.2~~0x59b689aa",
            "label": "nsubj",
            "title": "freq: 2",
            "to": "resident~art.2~~0x59b689aa",
            "value": 2
        },
        {
            "from": "feel~art.2~~0x59b689aa",
            "id": "feel~art.2~~0x59b689aa|desperate_measure~art.2~~0x59b689aa",
            "label": "ccomp",
            "title": "freq: 2",
            "to": "desperate_measure~art.2~~0x59b689aa",
            "value": 2
        },
        {
            "from": "petition~art.2~~0x59b6899f",
            "id": "petition~art.2~~0x59b6899f|oppose~art.2~~0x59b6899f",
            "label": "acl",
            "title": "freq: 2",
            "to": "oppose~art.2~~0x59b6899f",
            "value": 2
        },
        {
            "from": "meet~art.4~~0x59b689b8",
            "id": "meet~art.4~~0x59b689b8|town_hall~art.2~~0x59b689aa",
            "label": "nmod",
            "title": "freq: 2",
            "to": "town_hall~art.2~~0x59b689aa",
            "value": 2
        }
    ],
    "nodes": [
        {
            "color": "#ff7800",
            "group": "article",
            "id": "colour~art.2~~0x59b689a4",
            "label": "colour",
            "title": "*Freq: 1 <br> *Sen_Score: 0.0 <br> *Sentiment: {\"pos_count\": 0, \"neu_count\": 1, \"neg_count\": 0} <br> *Group_ids: art.2",
            "value": 1
        },
        {
            "color": "#ff2800",
            "group": "article",
            "id": "be~art.1~~0x59b6899c",
            "label": "be",
            "title": "*Freq: 10 <br> *Sen_Score: -0.2 <br> *Sentiment: {\"pos_count\": 3, \"neu_count\": 0, \"neg_count\": 5} <br> *Group_ids: art.0,art.1,art.2,art.3",
            "value": 10
        },
        {
            "color": "#ff7800",
            "group": "article",
            "id": "oppose~art.2~~0x59b6899f",
            "label": "oppose",
            "title": "*Freq: 1 <br> *Sen_Score: 0.0 <br> *Sentiment: {\"pos_count\": 0, \"neu_count\": 1, \"neg_count\": 0} <br> *Group_ids: art.2",
            "value": 1
        },
        {
            "color": "#ffa000",
            "group": "article",
            "id": "wheelie~art.1~~0x59b68994",
            "label": "wheelie",
            "title": "*Freq: 1 <br> *Sen_Score: 0.1 <br> *Sentiment: {\"pos_count\": 1, \"neu_count\": 0, \"neg_count\": 0} <br> *Group_ids: art.1",
            "value": 1
        },
        {
            "color": "#ff7800",
            "group": "article",
            "id": "follow~art.4~~0x59b689b6",
            "label": "follow",
            "title": "*Freq: 1 <br> *Sen_Score: 0.0 <br> *Sentiment: {\"pos_count\": 0, \"neu_count\": 1, \"neg_count\": 0} <br> *Group_ids: art.4",
            "value": 1
        },
        {
            "color": "#ff7800",
            "group": "article",
            "id": "wa~art.2~~0x59b689aa",
            "label": "wa",
            "title": "*Freq: 2 <br> *Sen_Score: 0.0 <br> *Sentiment: {\"pos_count\": 1, \"neu_count\": 0, \"neg_count\": 1} <br> *Group_ids: art.1,art.2",
            "value": 2
        },
        {
            "color": "#ff7800",
            "group": "article",
            "id": "public~art.4~~0x59b689b8",
            "label": "public",
            "title": "*Freq: 1 <br> *Sen_Score: 0.0 <br> *Sentiment: {\"pos_count\": 0, \"neu_count\": 1, \"neg_count\": 0} <br> *Group_ids: art.4",
            "value": 1
        },
        {
            "color": "#ff5000",
            "group": "article",
            "id": "tell~art.2~~0x59b689aa",
            "label": "tell",
            "title": "*Freq: 1 <br> *Sen_Score: -0.1 <br> *Sentiment: {\"pos_count\": 0, \"neu_count\": 0, \"neg_count\": 1} <br> *Group_ids: art.2",
            "value": 1
        },
        {
            "color": "#ffa000",
            "group": "article",
            "id": "environmentally~art.0~~0x59b6898d",
            "label": "environmentally",
            "title": "*Freq: 1 <br> *Sen_Score: 0.1 <br> *Sentiment: {\"pos_count\": 1, \"neu_count\": 0, \"neg_count\": 0} <br> *Group_ids: art.0",
            "value": 1
        },
        {
            "color": "#ff5000",
            "group": "article",
            "id": "motion~art.1~~0x59b68999",
            "label": "motion",
            "title": "*Freq: 1 <br> *Sen_Score: -0.1 <br> *Sentiment: {\"pos_count\": 0, \"neu_count\": 0, \"neg_count\": 1} <br> *Group_ids: art.1",
            "value": 1
        },
        {
            "color": "#ff5000",
            "group": "article",
            "id": "empty~art.2~~0x59b689a6",
            "label": "empty",
            "title": "*Freq: 1 <br> *Sen_Score: -0.1 <br> *Sentiment: {\"pos_count\": 0, \"neu_count\": 0, \"neg_count\": 1} <br> *Group_ids: art.2",
            "value": 1
        },
        {
            "color": "#ffa000",
            "group": "article",
            "id": "england~art.1~~0x59b68994",
            "label": "england",
            "title": "*Freq: 1 <br> *Sen_Score: 0.1 <br> *Sentiment: {\"pos_count\": 1, \"neu_count\": 0, \"neg_count\": 0} <br> *Group_ids: art.1",
            "value": 1
        },
        {
            "color": "#ff7800",
            "group": "article",
            "id": "local~art.0~~0x59b6898d",
            "label": "local",
            "title": "*Freq: 2 <br> *Sen_Score: 0.0 <br> *Sentiment: {\"pos_count\": 1, \"neu_count\": 0, \"neg_count\": 1} <br> *Group_ids: art.0,art.3",
            "value": 2
        },
        {
            "color": "#ff2800",
            "group": "article",
            "id": "desperate_measure~art.2~~0x59b689aa",
            "label": "desperate_measure",
            "title": "*Freq: 2 <br> *Sen_Score: -0.2 <br> *Sentiment: {\"pos_count\": 0, \"neu_count\": 0, \"neg_count\": 2} <br> *Group_ids: art.0,art.2",
            "value": 2
        },
        {
            "color": "#ff5000",
            "group": "article",
            "id": "accuse~art.1~~0x59b68999",
            "label": "accuse",
            "title": "*Freq: 1 <br> *Sen_Score: -0.1 <br> *Sentiment: {\"pos_count\": 0, \"neu_count\": 0, \"neg_count\": 1} <br> *Group_ids: art.1",
            "value": 1
        },
        {
            "color": "#ff5000",
            "group": "article",
            "id": "50_%~art.3~~0x59b689ae",
            "label": "50_%",
            "title": "*Freq: 1 <br> *Sen_Score: -0.1 <br> *Sentiment: {\"pos_count\": 0, \"neu_count\": 0, \"neg_count\": 1} <br> *Group_ids: art.3",
            "value": 1
        },
        {
            "color": "#ff5000",
            "group": "article",
            "id": "waste_management~art.3~~0x59b689b3",
            "label": "waste_management",
            "title": "*Freq: 1 <br> *Sen_Score: -0.1 <br> *Sentiment: {\"pos_count\": 0, \"neu_count\": 0, \"neg_count\": 1} <br> *Group_ids: art.3",
            "value": 1
        },
        {
            "color": "#ff7800",
            "group": "article",
            "id": "new_initiative~art.2~~0x59b6899f",
            "label": "new_initiative",
            "title": "*Freq: 1 <br> *Sen_Score: 0.0 <br> *Sentiment: {\"pos_count\": 0, \"neu_count\": 1, \"neg_count\": 0} <br> *Group_ids: art.2",
            "value": 1
        },
        {
            "color": "#ff7800",
            "group": "article",
            "id": "vermin~art.0~~0x59b6898d",
            "label": "vermin",
            "title": "*Freq: 2 <br> *Sen_Score: 0.0 <br> *Sentiment: {\"pos_count\": 1, \"neu_count\": 0, \"neg_count\": 1} <br> *Group_ids: art.0,art.1",
            "value": 2
        },
        {
            "color": "#ffa000",
            "group": "article",
            "id": "friendly_borough~art.0~~0x59b6898d",
            "label": "friendly_borough",
            "title": "*Freq: 1 <br> *Sen_Score: 0.1 <br> *Sentiment: {\"pos_count\": 1, \"neu_count\": 0, \"neg_count\": 0} <br> *Group_ids: art.0",
            "value": 1
        },
        {
            "color": "#ff5000",
            "group": "article",
            "id": "labour~art.3~~0x59b689ae",
            "label": "labour",
            "title": "*Freq: 1 <br> *Sen_Score: -0.1 <br> *Sentiment: {\"pos_count\": 0, \"neu_count\": 0, \"neg_count\": 1} <br> *Group_ids: art.3",
            "value": 1
        },
        {
            "color": "#ff7800",
            "group": "article",
            "id": "councillor~art.1~~0x59b68999",
            "label": "councillor",
            "title": "*Freq: 2 <br> *Sen_Score: 0.0 <br> *Sentiment: {\"pos_count\": 1, \"neu_count\": 0, \"neg_count\": 1} <br> *Group_ids: art.1",
            "value": 2
        },
        {
            "color": "#ffa000",
            "group": "article",
            "id": "labour-run_council~art.2~~0x59b689a8",
            "label": "labour-run_council",
            "title": "*Freq: 1 <br> *Sen_Score: 0.1 <br> *Sentiment: {\"pos_count\": 1, \"neu_count\": 0, \"neg_count\": 0} <br> *Group_ids: art.2",
            "value": 1
        },
        {
            "color": "#ffa000",
            "group": "article",
            "id": "council~art.3~~0x59b689ae",
            "label": "council",
            "title": "*Freq: 3 <br> *Sen_Score: 0.1 <br> *Sentiment: {\"pos_count\": 2, \"neu_count\": 0, \"neg_count\": 1} <br> *Group_ids: art.0,art.1,art.3",
            "value": 3
        },
        {
            "color": "#ff5000",
            "group": "article",
            "id": "parliament~art.3~~0x59b689b3",
            "label": "parliament",
            "title": "*Freq: 1 <br> *Sen_Score: -0.1 <br> *Sentiment: {\"pos_count\": 0, \"neu_count\": 0, \"neg_count\": 1} <br> *Group_ids: art.3",
            "value": 1
        },
        {
            "color": "#ff5000",
            "group": "article",
            "id": "responsibility~art.3~~0x59b689b3",
            "label": "responsibility",
            "title": "*Freq: 1 <br> *Sen_Score: -0.1 <br> *Sentiment: {\"pos_count\": 0, \"neu_count\": 0, \"neg_count\": 1} <br> *Group_ids: art.3",
            "value": 1
        },
        {
            "color": "#ffa000",
            "group": "article",
            "id": "fly-tipping~art.0~~0x59b6898d",
            "label": "fly-tipping",
            "title": "*Freq: 1 <br> *Sen_Score: 0.1 <br> *Sentiment: {\"pos_count\": 1, \"neu_count\": 0, \"neg_count\": 0} <br> *Group_ids: art.0",
            "value": 1
        },
        {
            "color": "#ff5000",
            "group": "article",
            "id": "opponent~art.1~~0x59b68999",
            "label": "opponent",
            "title": "*Freq: 1 <br> *Sen_Score: -0.1 <br> *Sentiment: {\"pos_count\": 0, \"neu_count\": 0, \"neg_count\": 1} <br> *Group_ids: art.1",
            "value": 1
        },
        {
            "color": "#ff7800",
            "group": "article",
            "id": "people~art.2~~0x59b6899f",
            "label": "people",
            "title": "*Freq: 1 <br> *Sen_Score: 0.0 <br> *Sentiment: {\"pos_count\": 0, \"neu_count\": 1, \"neg_count\": 0} <br> *Group_ids: art.2",
            "value": 1
        },
        {
            "color": "#ffa000",
            "group": "article",
            "id": "week~art.1~~0x59b68994",
            "label": "week",
            "title": "*Freq: 3 <br> *Sen_Score: 0.1 <br> *Sentiment: {\"pos_count\": 1, \"neu_count\": 1, \"neg_count\": 0} <br> *Group_ids: art.4,art.1,art.2",
            "value": 3
        },
        {
            "color": "#ff5000",
            "group": "article",
            "id": "warn~art.1~~0x59b68999",
            "label": "warn",
            "title": "*Freq: 1 <br> *Sen_Score: -0.1 <br> *Sentiment: {\"pos_count\": 0, \"neu_count\": 0, \"neg_count\": 1} <br> *Group_ids: art.1",
            "value": 1
        },
        {
            "color": "#ffa000",
            "group": "article",
            "id": "fox~art.0~~0x59b6898d",
            "label": "fox",
            "title": "*Freq: 1 <br> *Sen_Score: 0.1 <br> *Sentiment: {\"pos_count\": 1, \"neu_count\": 0, \"neg_count\": 0} <br> *Group_ids: art.0",
            "value": 1
        },
        {
            "color": "#ff5000",
            "group": "article",
            "id": "household~art.2~~0x59b689a1",
            "label": "household",
            "title": "*Freq: 1 <br> *Sen_Score: -0.1 <br> *Sentiment: {\"pos_count\": 0, \"neu_count\": 0, \"neg_count\": 1} <br> *Group_ids: art.2",
            "value": 1
        },
        {
            "color": "#ffa000",
            "group": "article",
            "id": "part~art.2~~0x59b689a8",
            "label": "part",
            "title": "*Freq: 1 <br> *Sen_Score: 0.1 <br> *Sentiment: {\"pos_count\": 1, \"neu_count\": 0, \"neg_count\": 0} <br> *Group_ids: art.2",
            "value": 1
        },
        {
            "color": "#ffa000",
            "group": "article",
            "id": "insist~art.0~~0x59b6898d",
            "label": "insist",
            "title": "*Freq: 1 <br> *Sen_Score: 0.1 <br> *Sentiment: {\"pos_count\": 1, \"neu_count\": 0, \"neg_count\": 0} <br> *Group_ids: art.0",
            "value": 1
        },
        {
            "color": "#ff5000",
            "group": "article",
            "id": "ivan_lewis~art.3~~0x59b689ae",
            "label": "ivan_lewis",
            "title": "*Freq: 1 <br> *Sen_Score: -0.1 <br> *Sentiment: {\"pos_count\": 0, \"neu_count\": 0, \"neg_count\": 1} <br> *Group_ids: art.3",
            "value": 1
        },
        {
            "color": "#ffa000",
            "group": "article",
            "id": "unanimously~art.1~~0x59b68996",
            "label": "unanimously",
            "title": "*Freq: 1 <br> *Sen_Score: 0.1 <br> *Sentiment: {\"pos_count\": 1, \"neu_count\": 0, \"neg_count\": 0} <br> *Group_ids: art.1",
            "value": 1
        },
        {
            "color": "#ffa000",
            "group": "article",
            "id": "night~art.1~~0x59b68996",
            "label": "night",
            "title": "*Freq: 2 <br> *Sen_Score: 0.1 <br> *Sentiment: {\"pos_count\": 1, \"neu_count\": 1, \"neg_count\": 0} <br> *Group_ids: art.4,art.1",
            "value": 2
        },
        {
            "color": "#ffa000",
            "group": "article",
            "id": "claim~art.2~~0x59b689a8",
            "label": "claim",
            "title": "*Freq: 1 <br> *Sen_Score: 0.1 <br> *Sentiment: {\"pos_count\": 1, \"neu_count\": 0, \"neg_count\": 0} <br> *Group_ids: art.2",
            "value": 1
        },
        {
            "color": "#ffa000",
            "group": "article",
            "id": "new_move~art.0~~0x59b6898d",
            "label": "new_move",
            "title": "*Freq: 1 <br> *Sen_Score: 0.1 <br> *Sentiment: {\"pos_count\": 1, \"neu_count\": 0, \"neg_count\": 0} <br> *Group_ids: art.0",
            "value": 1
        },
        {
            "color": "#ffa000",
            "group": "article",
            "id": "spend~art.1~~0x59b6899c",
            "label": "spend",
            "title": "*Freq: 1 <br> *Sen_Score: 0.1 <br> *Sentiment: {\"pos_count\": 1, \"neu_count\": 0, \"neg_count\": 0} <br> *Group_ids: art.1",
            "value": 1
        },
        {
            "color": "#ff7800",
            "group": "article",
            "id": "october~art.2~~0x59b6899f",
            "label": "october",
            "title": "*Freq: 1 <br> *Sen_Score: 0.0 <br> *Sentiment: {\"pos_count\": 0, \"neu_count\": 1, \"neg_count\": 0} <br> *Group_ids: art.2",
            "value": 1
        },
        {
            "color": "#ff5000",
            "group": "article",
            "id": "decision~art.3~~0x59b689ae",
            "label": "decision",
            "title": "*Freq: 2 <br> *Sen_Score: -0.1 <br> *Sentiment: {\"pos_count\": 0, \"neu_count\": 1, \"neg_count\": 1} <br> *Group_ids: art.4,art.3",
            "value": 2
        },
        {
            "color": "#ff5000",
            "group": "article",
            "id": "coalition~art.3~~0x59b689ae",
            "label": "coalition",
            "title": "*Freq: 1 <br> *Sen_Score: -0.1 <br> *Sentiment: {\"pos_count\": 0, \"neu_count\": 0, \"neg_count\": 1} <br> *Group_ids: art.3",
            "value": 1
        },
        {
            "color": "#ff2800",
            "group": "article",
            "id": "year~art.4~~0x59b689b6",
            "label": "year",
            "title": "*Freq: 3 <br> *Sen_Score: -0.2 <br> *Sentiment: {\"pos_count\": 0, \"neu_count\": 1, \"neg_count\": 2} <br> *Group_ids: art.4,art.2,art.3",
            "value": 3
        },
        {
            "color": "#ff5000",
            "group": "article",
            "id": "next~art.2~~0x59b689aa",
            "label": "next",
            "title": "*Freq: 1 <br> *Sen_Score: -0.1 <br> *Sentiment: {\"pos_count\": 0, \"neu_count\": 0, \"neg_count\": 1} <br> *Group_ids: art.2",
            "value": 1
        },
        {
            "color": "#ff6400",
            "group": "article",
            "id": "bury~art.1~~0x59b68996",
            "label": "bury",
            "title": "*Freq: 3 <br> *Sen_Score: 0.2 <br> *Sentiment: {\"pos_count\": 2, \"neu_count\": 0, \"neg_count\": 0} <br> *Group_ids: art.4,art.1,art.2",
            "value": 3
        },
        {
            "color": "#ff5000",
            "group": "article",
            "id": "bury_council~art.3~~0x59b689b1",
            "label": "bury_council",
            "title": "*Freq: 1 <br> *Sen_Score: -0.1 <br> *Sentiment: {\"pos_count\": 0, \"neu_count\": 0, \"neg_count\": 1} <br> *Group_ids: art.3",
            "value": 1
        },
        {
            "color": "#ff7800",
            "group": "article",
            "id": "speak~art.4~~0x59b689b8",
            "label": "speak",
            "title": "*Freq: 1 <br> *Sen_Score: 0.0 <br> *Sentiment: {\"pos_count\": 0, \"neu_count\": 1, \"neg_count\": 0} <br> *Group_ids: art.4",
            "value": 1
        },
        {
            "color": "#ff5000",
            "group": "article",
            "id": "mean~art.3~~0x59b689b1",
            "label": "mean",
            "title": "*Freq: 1 <br> *Sen_Score: -0.1 <br> *Sentiment: {\"pos_count\": 0, \"neu_count\": 0, \"neg_count\": 1} <br> *Group_ids: art.3",
            "value": 1
        },
        {
            "color": "#ffa000",
            "group": "article",
            "id": "strategy~art.2~~0x59b689a8",
            "label": "strategy",
            "title": "*Freq: 1 <br> *Sen_Score: 0.1 <br> *Sentiment: {\"pos_count\": 1, \"neu_count\": 0, \"neg_count\": 0} <br> *Group_ids: art.2",
            "value": 1
        },
        {
            "color": "#ffa000",
            "group": "article",
            "id": "scrap~art.1~~0x59b68994",
            "label": "scrap",
            "title": "*Freq: 1 <br> *Sen_Score: 0.1 <br> *Sentiment: {\"pos_count\": 1, \"neu_count\": 0, \"neg_count\": 0} <br> *Group_ids: art.1",
            "value": 1
        },
        {
            "color": "#ff5000",
            "group": "article",
            "id": "lyndsay_warner~art.0~~0x59b68990",
            "label": "lyndsay_warner",
            "title": "*Freq: 1 <br> *Sen_Score: -0.1 <br> *Sentiment: {\"pos_count\": 0, \"neu_count\": 0, \"neg_count\": 1} <br> *Group_ids: art.0",
            "value": 1
        },
        {
            "color": "#ff5000",
            "group": "article",
            "id": "effective_cut~art.3~~0x59b689ae",
            "label": "effective_cut",
            "title": "*Freq: 1 <br> *Sen_Score: -0.1 <br> *Sentiment: {\"pos_count\": 0, \"neu_count\": 0, \"neg_count\": 1} <br> *Group_ids: art.3",
            "value": 1
        },
        {
            "color": "#ff7800",
            "group": "article",
            "id": "monthly~art.2~~0x59b689a4",
            "label": "monthly",
            "title": "*Freq: 1 <br> *Sen_Score: 0.0 <br> *Sentiment: {\"pos_count\": 0, \"neu_count\": 1, \"neg_count\": 0} <br> *Group_ids: art.2",
            "value": 1
        },
        {
            "color": "#ff2800",
            "group": "article",
            "id": "mp~art.3~~0x59b689b3",
            "label": "mp",
            "title": "*Freq: 2 <br> *Sen_Score: -0.2 <br> *Sentiment: {\"pos_count\": 0, \"neu_count\": 0, \"neg_count\": 2} <br> *Group_ids: art.3",
            "value": 2
        },
        {
            "color": "#ff7800",
            "group": "article",
            "id": "wale~art.4~~0x59b689b6",
            "label": "wale",
            "title": "*Freq: 1 <br> *Sen_Score: 0.0 <br> *Sentiment: {\"pos_count\": 0, \"neu_count\": 1, \"neg_count\": 0} <br> *Group_ids: art.4",
            "value": 1
        },
        {
            "color": "#ffa000",
            "group": "article",
            "id": "pass~art.1~~0x59b68996",
            "label": "pass",
            "title": "*Freq: 1 <br> *Sen_Score: 0.1 <br> *Sentiment: {\"pos_count\": 1, \"neu_count\": 0, \"neg_count\": 0} <br> *Group_ids: art.1",
            "value": 1
        },
        {
            "color": "#ff2800",
            "group": "article",
            "id": "impose~art.3~~0x59b689b1",
            "label": "impose",
            "title": "*Freq: 2 <br> *Sen_Score: -0.2 <br> *Sentiment: {\"pos_count\": 0, \"neu_count\": 0, \"neg_count\": 2} <br> *Group_ids: art.3",
            "value": 2
        },
        {
            "color": "#ff5000",
            "group": "article",
            "id": "blog~art.3~~0x59b689b1",
            "label": "blog",
            "title": "*Freq: 1 <br> *Sen_Score: -0.1 <br> *Sentiment: {\"pos_count\": 0, \"neu_count\": 0, \"neg_count\": 1} <br> *Group_ids: art.3",
            "value": 1
        },
        {
            "color": "#ff5000",
            "group": "article",
            "id": "general_waste~art.2~~0x59b689a1",
            "label": "general_waste",
            "title": "*Freq: 1 <br> *Sen_Score: -0.1 <br> *Sentiment: {\"pos_count\": 0, \"neu_count\": 0, \"neg_count\": 1} <br> *Group_ids: art.2",
            "value": 1
        },
        {
            "color": "#ff7800",
            "group": "article",
            "id": "glass~art.2~~0x59b689a4",
            "label": "glass",
            "title": "*Freq: 1 <br> *Sen_Score: 0.0 <br> *Sentiment: {\"pos_count\": 0, \"neu_count\": 1, \"neg_count\": 0} <br> *Group_ids: art.2",
            "value": 1
        },
        {
            "color": "#ff2800",
            "group": "article",
            "id": "many~art.2~~0x59b689aa",
            "label": "many",
            "title": "*Freq: 2 <br> *Sen_Score: -0.2 <br> *Sentiment: {\"pos_count\": 0, \"neu_count\": 0, \"neg_count\": 2} <br> *Group_ids: art.2,art.3",
            "value": 2
        },
        {
            "color": "#ff7800",
            "group": "article",
            "id": "falkirk~art.4~~0x59b689b6",
            "label": "falkirk",
            "title": "*Freq: 1 <br> *Sen_Score: 0.0 <br> *Sentiment: {\"pos_count\": 0, \"neu_count\": 1, \"neg_count\": 0} <br> *Group_ids: art.4",
            "value": 1
        },
        {
            "color": "#ff7800",
            "group": "article",
            "id": "gwynedd_council~art.4~~0x59b689b6",
            "label": "gwynedd_council",
            "title": "*Freq: 1 <br> *Sen_Score: 0.0 <br> *Sentiment: {\"pos_count\": 0, \"neu_count\": 1, \"neg_count\": 0} <br> *Group_ids: art.4",
            "value": 1
        },
        {
            "color": "#ffa000",
            "group": "article",
            "id": "landfill_fee~art.2~~0x59b689a8",
            "label": "landfill_fee",
            "title": "*Freq: 1 <br> *Sen_Score: 0.1 <br> *Sentiment: {\"pos_count\": 1, \"neu_count\": 0, \"neg_count\": 0} <br> *Group_ids: art.2",
            "value": 1
        },
        {
            "color": "#ffa000",
            "group": "article",
            "id": "worker~art.1~~0x59b6899c",
            "label": "worker",
            "title": "*Freq: 1 <br> *Sen_Score: 0.1 <br> *Sentiment: {\"pos_count\": 1, \"neu_count\": 0, \"neg_count\": 0} <br> *Group_ids: art.1",
            "value": 1
        },
        {
            "color": "#ff5000",
            "group": "article",
            "id": "complain~art.3~~0x59b689b3",
            "label": "complain",
            "title": "*Freq: 1 <br> *Sen_Score: -0.1 <br> *Sentiment: {\"pos_count\": 0, \"neu_count\": 0, \"neg_count\": 1} <br> *Group_ids: art.3",
            "value": 1
        },
        {
            "color": "#ffa000",
            "group": "article",
            "id": "turn~art.2~~0x59b689a8",
            "label": "turn",
            "title": "*Freq: 1 <br> *Sen_Score: 0.1 <br> *Sentiment: {\"pos_count\": 1, \"neu_count\": 0, \"neg_count\": 0} <br> *Group_ids: art.2",
            "value": 1
        },
        {
            "color": "#ff5000",
            "group": "article",
            "id": "scaremongering~art.1~~0x59b68999",
            "label": "scaremongering",
            "title": "*Freq: 1 <br> *Sen_Score: -0.1 <br> *Sentiment: {\"pos_count\": 0, \"neu_count\": 0, \"neg_count\": 1} <br> *Group_ids: art.1",
            "value": 1
        },
        {
            "color": "#ff7800",
            "group": "article",
            "id": "attract~art.0~~0x59b6898d",
            "label": "attract",
            "title": "*Freq: 2 <br> *Sen_Score: 0.0 <br> *Sentiment: {\"pos_count\": 1, \"neu_count\": 0, \"neg_count\": 1} <br> *Group_ids: art.0,art.1",
            "value": 2
        },
        {
            "color": "#ff2800",
            "group": "article",
            "id": "cost~art.0~~0x59b6898f",
            "label": "cost",
            "title": "*Freq: 2 <br> *Sen_Score: -0.2 <br> *Sentiment: {\"pos_count\": 0, \"neu_count\": 0, \"neg_count\": 2} <br> *Group_ids: art.0,art.2",
            "value": 2
        },
        {
            "color": "#ffa000",
            "group": "article",
            "id": "lead~art.0~~0x59b6898d",
            "label": "lead",
            "title": "*Freq: 2 <br> *Sen_Score: 0.1 <br> *Sentiment: {\"pos_count\": 1, \"neu_count\": 1, \"neg_count\": 0} <br> *Group_ids: art.4,art.0",
            "value": 2
        },
        {
            "color": "#ff5000",
            "group": "article",
            "id": "rubbish~art.4~~0x59b689b6",
            "label": "rubbish",
            "title": "*Freq: 2 <br> *Sen_Score: -0.1 <br> *Sentiment: {\"pos_count\": 0, \"neu_count\": 1, \"neg_count\": 1} <br> *Group_ids: art.4,art.1",
            "value": 2
        },
        {
            "color": "#ff5000",
            "group": "article",
            "id": "change~art.2~~0x59b689a6",
            "label": "change",
            "title": "*Freq: 1 <br> *Sen_Score: -0.1 <br> *Sentiment: {\"pos_count\": 0, \"neu_count\": 0, \"neg_count\": 1} <br> *Group_ids: art.2",
            "value": 1
        },
        {
            "color": "#ff7800",
            "group": "article",
            "id": "scotland~art.4~~0x59b689b6",
            "label": "scotland",
            "title": "*Freq: 1 <br> *Sen_Score: 0.0 <br> *Sentiment: {\"pos_count\": 0, \"neu_count\": 1, \"neg_count\": 0} <br> *Group_ids: art.4",
            "value": 1
        },
        {
            "color": "#ffa000",
            "group": "article",
            "id": "first~art.1~~0x59b68994",
            "label": "first",
            "title": "*Freq: 1 <br> *Sen_Score: 0.1 <br> *Sentiment: {\"pos_count\": 1, \"neu_count\": 0, \"neg_count\": 0} <br> *Group_ids: art.1",
            "value": 1
        },
        {
            "color": "#ff7800",
            "group": "article",
            "id": "recycle~art.2~~0x59b689a1",
            "label": "recycle",
            "title": "*Freq: 2 <br> *Sen_Score: 0.0 <br> *Sentiment: {\"pos_count\": 1, \"neu_count\": 0, \"neg_count\": 1} <br> *Group_ids: art.2",
            "value": 2
        },
        {
            "color": "#ff5000",
            "group": "article",
            "id": "risk~art.3~~0x59b689b1",
            "label": "risk",
            "title": "*Freq: 1 <br> *Sen_Score: -0.1 <br> *Sentiment: {\"pos_count\": 0, \"neu_count\": 0, \"neg_count\": 1} <br> *Group_ids: art.3",
            "value": 1
        },
        {
            "color": "#ffa000",
            "group": "article",
            "id": "save~art.2~~0x59b689a8",
            "label": "save",
            "title": "*Freq: 3 <br> *Sen_Score: 0.1 <br> *Sentiment: {\"pos_count\": 2, \"neu_count\": 0, \"neg_count\": 1} <br> *Group_ids: art.1,art.2",
            "value": 3
        },
        {
            "color": "#ff5000",
            "group": "article",
            "id": "make~art.0~~0x59b6898d",
            "label": "make",
            "title": "*Freq: 3 <br> *Sen_Score: -0.1 <br> *Sentiment: {\"pos_count\": 1, \"neu_count\": 0, \"neg_count\": 2} <br> *Group_ids: art.0,art.2,art.3",
            "value": 3
        },
        {
            "color": "#ff5000",
            "group": "article",
            "id": "lie~art.3~~0x59b689b3",
            "label": "lie",
            "title": "*Freq: 1 <br> *Sen_Score: -0.1 <br> *Sentiment: {\"pos_count\": 0, \"neu_count\": 0, \"neg_count\": 1} <br> *Group_ids: art.3",
            "value": 1
        },
        {
            "color": "#ff5000",
            "group": "article",
            "id": "budget~art.3~~0x59b689ae",
            "label": "budget",
            "title": "*Freq: 1 <br> *Sen_Score: -0.1 <br> *Sentiment: {\"pos_count\": 0, \"neu_count\": 0, \"neg_count\": 1} <br> *Group_ids: art.3",
            "value": 1
        },
        {
            "color": "#ff7800",
            "group": "article",
            "id": "paper~art.2~~0x59b689a4",
            "label": "paper",
            "title": "*Freq: 1 <br> *Sen_Score: 0.0 <br> *Sentiment: {\"pos_count\": 0, \"neu_count\": 1, \"neg_count\": 0} <br> *Group_ids: art.2",
            "value": 1
        },
        {
            "color": "#ffa000",
            "group": "article",
            "id": "start~art.1~~0x59b68994",
            "label": "start",
            "title": "*Freq: 2 <br> *Sen_Score: 0.1 <br> *Sentiment: {\"pos_count\": 1, \"neu_count\": 1, \"neg_count\": 0} <br> *Group_ids: art.4,art.1",
            "value": 2
        },
        {
            "color": "#ff7800",
            "group": "article",
            "id": "introduce~art.2~~0x59b6899f",
            "label": "introduce",
            "title": "*Freq: 1 <br> *Sen_Score: 0.0 <br> *Sentiment: {\"pos_count\": 0, \"neu_count\": 1, \"neg_count\": 0} <br> *Group_ids: art.2",
            "value": 1
        },
        {
            "color": "#ff5000",
            "group": "article",
            "id": "unprecedented~art.3~~0x59b689b1",
            "label": "unprecedented",
            "title": "*Freq: 1 <br> *Sen_Score: -0.1 <br> *Sentiment: {\"pos_count\": 0, \"neu_count\": 0, \"neg_count\": 1} <br> *Group_ids: art.3",
            "value": 1
        },
        {
            "color": "#ff7800",
            "group": "article",
            "id": "member~art.4~~0x59b689b8",
            "label": "member",
            "title": "*Freq: 1 <br> *Sen_Score: 0.0 <br> *Sentiment: {\"pos_count\": 0, \"neu_count\": 1, \"neg_count\": 0} <br> *Group_ids: art.4",
            "value": 1
        },
        {
            "color": "#ff5000",
            "group": "article",
            "id": "line_service~art.3~~0x59b689b1",
            "label": "line_service",
            "title": "*Freq: 1 <br> *Sen_Score: -0.1 <br> *Sentiment: {\"pos_count\": 0, \"neu_count\": 0, \"neg_count\": 1} <br> *Group_ids: art.3",
            "value": 1
        },
        {
            "color": "#ff5000",
            "group": "article",
            "id": "used~art.2~~0x59b689a1",
            "label": "used",
            "title": "*Freq: 1 <br> *Sen_Score: -0.1 <br> *Sentiment: {\"pos_count\": 0, \"neu_count\": 0, \"neg_count\": 1} <br> *Group_ids: art.2",
            "value": 1
        },
        {
            "color": "#ff7800",
            "group": "article",
            "id": "plastic~art.2~~0x59b689a4",
            "label": "plastic",
            "title": "*Freq: 1 <br> *Sen_Score: 0.0 <br> *Sentiment: {\"pos_count\": 0, \"neu_count\": 1, \"neg_count\": 0} <br> *Group_ids: art.2",
            "value": 1
        },
        {
            "color": "#ff7800",
            "group": "article",
            "id": "controversial_decision~art.0~~0x59b68990",
            "label": "controversial_decision",
            "title": "*Freq: 2 <br> *Sen_Score: 0.0 <br> *Sentiment: {\"pos_count\": 1, \"neu_count\": 0, \"neg_count\": 1} <br> *Group_ids: art.0,art.1",
            "value": 2
        },
        {
            "color": "#ff5000",
            "group": "article",
            "id": "receive~art.3~~0x59b689b3",
            "label": "receive",
            "title": "*Freq: 1 <br> *Sen_Score: -0.1 <br> *Sentiment: {\"pos_count\": 0, \"neu_count\": 0, \"neg_count\": 1} <br> *Group_ids: art.3",
            "value": 1
        },
        {
            "color": "#ff5000",
            "group": "article",
            "id": "local_government~art.3~~0x59b689b3",
            "label": "local_government",
            "title": "*Freq: 1 <br> *Sen_Score: -0.1 <br> *Sentiment: {\"pos_count\": 0, \"neu_count\": 0, \"neg_count\": 1} <br> *Group_ids: art.3",
            "value": 1
        },
        {
            "color": "#ff2800",
            "group": "article",
            "id": "say~art.3~~0x59b689b1",
            "label": "say",
            "title": "*Freq: 2 <br> *Sen_Score: -0.2 <br> *Sentiment: {\"pos_count\": 0, \"neu_count\": 0, \"neg_count\": 2} <br> *Group_ids: art.3",
            "value": 2
        },
        {
            "color": "#ff0000",
            "group": "article",
            "id": "cut~art.0~~0x59b6898f",
            "label": "cut",
            "title": "*Freq: 3 <br> *Sen_Score: -0.3 <br> *Sentiment: {\"pos_count\": 0, \"neu_count\": 0, \"neg_count\": 3} <br> *Group_ids: art.0,art.2,art.3",
            "value": 3
        },
        {
            "color": "#ffa000",
            "group": "article",
            "id": "waste_borough~art.2~~0x59b689a8",
            "label": "waste_borough",
            "title": "*Freq: 1 <br> *Sen_Score: 0.1 <br> *Sentiment: {\"pos_count\": 1, \"neu_count\": 0, \"neg_count\": 0} <br> *Group_ids: art.2",
            "value": 1
        },
        {
            "color": "#ff7800",
            "group": "article",
            "id": "green~art.2~~0x59b689a4",
            "label": "green",
            "title": "*Freq: 1 <br> *Sen_Score: 0.0 <br> *Sentiment: {\"pos_count\": 0, \"neu_count\": 1, \"neg_count\": 0} <br> *Group_ids: art.2",
            "value": 1
        },
        {
            "color": "#ffa000",
            "group": "article",
            "id": "wednesday~art.1~~0x59b68996",
            "label": "wednesday",
            "title": "*Freq: 2 <br> *Sen_Score: 0.1 <br> *Sentiment: {\"pos_count\": 1, \"neu_count\": 1, \"neg_count\": 0} <br> *Group_ids: art.4,art.1",
            "value": 2
        },
        {
            "color": "#ffa000",
            "group": "article",
            "id": "manchester~art.1~~0x59b68994",
            "label": "manchester",
            "title": "*Freq: 1 <br> *Sen_Score: 0.1 <br> *Sentiment: {\"pos_count\": 1, \"neu_count\": 0, \"neg_count\": 0} <br> *Group_ids: art.1",
            "value": 1
        },
        {
            "color": "#ff5000",
            "group": "article",
            "id": "pile~art.1~~0x59b68999",
            "label": "pile",
            "title": "*Freq: 1 <br> *Sen_Score: -0.1 <br> *Sentiment: {\"pos_count\": 0, \"neu_count\": 0, \"neg_count\": 1} <br> *Group_ids: art.1",
            "value": 1
        },
        {
            "color": "#ffa000",
            "group": "article",
            "id": "current_collection~art.1~~0x59b68994",
            "label": "current_collection",
            "title": "*Freq: 1 <br> *Sen_Score: 0.1 <br> *Sentiment: {\"pos_count\": 1, \"neu_count\": 0, \"neg_count\": 0} <br> *Group_ids: art.1",
            "value": 1
        },
        {
            "color": "#ff6400",
            "group": "article",
            "id": "money~art.1~~0x59b6899c",
            "label": "money",
            "title": "*Freq: 2 <br> *Sen_Score: 0.2 <br> *Sentiment: {\"pos_count\": 2, \"neu_count\": 0, \"neg_count\": 0} <br> *Group_ids: art.1,art.2",
            "value": 2
        },
        {
            "color": "#ff6400",
            "group": "article",
            "id": "increase~art.1~~0x59b68996",
            "label": "increase",
            "title": "*Freq: 2 <br> *Sen_Score: 0.2 <br> *Sentiment: {\"pos_count\": 2, \"neu_count\": 0, \"neg_count\": 0} <br> *Group_ids: art.0,art.1",
            "value": 2
        },
        {
            "color": "#ffa000",
            "group": "article",
            "id": "collect~art.1~~0x59b68994",
            "label": "collect",
            "title": "*Freq: 3 <br> *Sen_Score: 0.1 <br> *Sentiment: {\"pos_count\": 1, \"neu_count\": 1, \"neg_count\": 0} <br> *Group_ids: art.4,art.1,art.2",
            "value": 3
        },
        {
            "color": "#ff5000",
            "group": "article",
            "id": "flat~art.2~~0x59b689a6",
            "label": "flat",
            "title": "*Freq: 1 <br> *Sen_Score: -0.1 <br> *Sentiment: {\"pos_count\": 0, \"neu_count\": 0, \"neg_count\": 1} <br> *Group_ids: art.2",
            "value": 1
        },
        {
            "color": "#ff5000",
            "group": "article",
            "id": "other_issue~art.3~~0x59b689b3",
            "label": "other_issue",
            "title": "*Freq: 1 <br> *Sen_Score: -0.1 <br> *Sentiment: {\"pos_count\": 0, \"neu_count\": 0, \"neg_count\": 1} <br> *Group_ids: art.3",
            "value": 1
        },
        {
            "color": "#ff7800",
            "group": "article",
            "id": "blue~art.2~~0x59b689a4",
            "label": "blue",
            "title": "*Freq: 1 <br> *Sen_Score: 0.0 <br> *Sentiment: {\"pos_count\": 0, \"neu_count\": 1, \"neg_count\": 0} <br> *Group_ids: art.2",
            "value": 1
        },
        {
            "color": "#ffa000",
            "group": "article",
            "id": "social~art.1~~0x59b6899c",
            "label": "social",
            "title": "*Freq: 1 <br> *Sen_Score: 0.1 <br> *Sentiment: {\"pos_count\": 1, \"neu_count\": 0, \"neg_count\": 0} <br> *Group_ids: art.1",
            "value": 1
        },
        {
            "color": "#ff5000",
            "group": "article",
            "id": "complaint~art.3~~0x59b689b3",
            "label": "complaint",
            "title": "*Freq: 1 <br> *Sen_Score: -0.1 <br> *Sentiment: {\"pos_count\": 0, \"neu_count\": 0, \"neg_count\": 1} <br> *Group_ids: art.3",
            "value": 1
        },
        {
            "color": "#ff7800",
            "group": "central",
            "id": "Central~title~_~0x59b68986",
            "label": "Rubbish? ...",
            "title": "*Freq: 1 <br> *Sen_Score: 0.0 <br> *Sentiment: {\"pos_count\": 0, \"neu_count\": 1, \"neg_count\": 0} <br> *Group_ids: central.group",
            "value": 1
        },
        {
            "color": "#ff5000",
            "group": "article",
            "id": "serve~art.2~~0x59b689a6",
            "label": "serve",
            "title": "*Freq: 1 <br> *Sen_Score: -0.1 <br> *Sentiment: {\"pos_count\": 0, \"neu_count\": 0, \"neg_count\": 1} <br> *Group_ids: art.2",
            "value": 1
        },
        {
            "color": "#ff5000",
            "group": "article",
            "id": "front~art.3~~0x59b689b1",
            "label": "front",
            "title": "*Freq: 1 <br> *Sen_Score: -0.1 <br> *Sentiment: {\"pos_count\": 0, \"neu_count\": 0, \"neg_count\": 1} <br> *Group_ids: art.3",
            "value": 1
        },
        {
            "color": "#ffa000",
            "group": "article",
            "id": "argue~art.1~~0x59b6899c",
            "label": "argue",
            "title": "*Freq: 1 <br> *Sen_Score: 0.1 <br> *Sentiment: {\"pos_count\": 1, \"neu_count\": 0, \"neg_count\": 0} <br> *Group_ids: art.1",
            "value": 1
        },
        {
            "color": "#ff5000",
            "group": "article",
            "id": "have~art.3~~0x59b689ae",
            "label": "have",
            "title": "*Freq: 1 <br> *Sen_Score: -0.1 <br> *Sentiment: {\"pos_count\": 0, \"neu_count\": 0, \"neg_count\": 1} <br> *Group_ids: art.3",
            "value": 1
        },
        {
            "color": "#ff5000",
            "group": "article",
            "id": "bin~art.2~~0x59b689a1",
            "label": "bin",
            "title": "*Freq: 4 <br> *Sen_Score: -0.1 <br> *Sentiment: {\"pos_count\": 1, \"neu_count\": 1, \"neg_count\": 2} <br> *Group_ids: art.1,art.2",
            "value": 4
        },
        {
            "color": "#ffa000",
            "group": "article",
            "id": "move~art.2~~0x59b689a8",
            "label": "move",
            "title": "*Freq: 1 <br> *Sen_Score: 0.1 <br> *Sentiment: {\"pos_count\": 1, \"neu_count\": 0, \"neg_count\": 0} <br> *Group_ids: art.2",
            "value": 1
        },
        {
            "color": "#ff5000",
            "group": "article",
            "id": "bin_collection~art.3~~0x59b689b3",
            "label": "bin_collection",
            "title": "*Freq: 1 <br> *Sen_Score: -0.1 <br> *Sentiment: {\"pos_count\": 0, \"neu_count\": 0, \"neg_count\": 1} <br> *Group_ids: art.3",
            "value": 1
        },
        {
            "color": "#ff5000",
            "group": "article",
            "id": "resident~art.2~~0x59b689aa",
            "label": "resident",
            "title": "*Freq: 1 <br> *Sen_Score: -0.1 <br> *Sentiment: {\"pos_count\": 0, \"neu_count\": 0, \"neg_count\": 1} <br> *Group_ids: art.2",
            "value": 1
        },
        {
            "color": "#ff5000",
            "group": "article",
            "id": "difficult~art.3~~0x59b689ae",
            "label": "difficult",
            "title": "*Freq: 1 <br> *Sen_Score: -0.1 <br> *Sentiment: {\"pos_count\": 0, \"neu_count\": 0, \"neg_count\": 1} <br> *Group_ids: art.3",
            "value": 1
        },
        {
            "color": "#ff7800",
            "group": "article",
            "id": "tip~art.1~~0x59b68996",
            "label": "tip",
            "title": "*Freq: 2 <br> *Sen_Score: 0.0 <br> *Sentiment: {\"pos_count\": 1, \"neu_count\": 0, \"neg_count\": 1} <br> *Group_ids: art.1",
            "value": 2
        },
        {
            "color": "#ffa000",
            "group": "article",
            "id": "boost~art.2~~0x59b689a8",
            "label": "boost",
            "title": "*Freq: 1 <br> *Sen_Score: 0.1 <br> *Sentiment: {\"pos_count\": 1, \"neu_count\": 0, \"neg_count\": 0} <br> *Group_ids: art.2",
            "value": 1
        },
        {
            "color": "#ff5000",
            "group": "article",
            "id": "grey~art.2~~0x59b689a1",
            "label": "grey",
            "title": "*Freq: 1 <br> *Sen_Score: -0.1 <br> *Sentiment: {\"pos_count\": 0, \"neu_count\": 0, \"neg_count\": 1} <br> *Group_ids: art.2",
            "value": 1
        },
        {
            "color": "#ffa000",
            "group": "article",
            "id": "fortnightly~art.1~~0x59b68994",
            "label": "fortnightly",
            "title": "*Freq: 1 <br> *Sen_Score: 0.1 <br> *Sentiment: {\"pos_count\": 1, \"neu_count\": 0, \"neg_count\": 0} <br> *Group_ids: art.1",
            "value": 1
        },
        {
            "color": "#ff5000",
            "group": "article",
            "id": "vote~art.1~~0x59b68999",
            "label": "vote",
            "title": "*Freq: 2 <br> *Sen_Score: -0.1 <br> *Sentiment: {\"pos_count\": 0, \"neu_count\": 1, \"neg_count\": 1} <br> *Group_ids: art.4,art.1",
            "value": 2
        },
        {
            "color": "#ff5000",
            "group": "article",
            "id": "con/dem_government~art.3~~0x59b689b1",
            "label": "con/dem_government",
            "title": "*Freq: 1 <br> *Sen_Score: -0.1 <br> *Sentiment: {\"pos_count\": 0, \"neu_count\": 0, \"neg_count\": 1} <br> *Group_ids: art.3",
            "value": 1
        },
        {
            "color": "#ff6400",
            "group": "article",
            "id": "fear~art.0~~0x59b6898d",
            "label": "fear",
            "title": "*Freq: 2 <br> *Sen_Score: 0.2 <br> *Sentiment: {\"pos_count\": 2, \"neu_count\": 0, \"neg_count\": 0} <br> *Group_ids: art.0,art.1",
            "value": 2
        },
        {
            "color": "#ff5000",
            "group": "article",
            "id": "communal~art.2~~0x59b689a6",
            "label": "communal",
            "title": "*Freq: 1 <br> *Sen_Score: -0.1 <br> *Sentiment: {\"pos_count\": 0, \"neu_count\": 0, \"neg_count\": 1} <br> *Group_ids: art.2",
            "value": 1
        },
        {
            "color": "#ffa000",
            "group": "article",
            "id": "fly~art.1~~0x59b68996",
            "label": "fly",
            "title": "*Freq: 1 <br> *Sen_Score: 0.1 <br> *Sentiment: {\"pos_count\": 1, \"neu_count\": 0, \"neg_count\": 0} <br> *Group_ids: art.1",
            "value": 1
        },
        {
            "color": "#ff5000",
            "group": "article",
            "id": "town_hall~art.2~~0x59b689aa",
            "label": "town_hall",
            "title": "*Freq: 2 <br> *Sen_Score: -0.1 <br> *Sentiment: {\"pos_count\": 0, \"neu_count\": 1, \"neg_count\": 1} <br> *Group_ids: art.4,art.2",
            "value": 2
        },
        {
            "color": "#ff5000",
            "group": "article",
            "id": "feel~art.2~~0x59b689aa",
            "label": "feel",
            "title": "*Freq: 1 <br> *Sen_Score: -0.1 <br> *Sentiment: {\"pos_count\": 0, \"neu_count\": 0, \"neg_count\": 1} <br> *Group_ids: art.2",
            "value": 1
        },
        {
            "color": "#ff7800",
            "group": "article",
            "id": "petition~art.2~~0x59b6899f",
            "label": "petition",
            "title": "*Freq: 1 <br> *Sen_Score: 0.0 <br> *Sentiment: {\"pos_count\": 0, \"neu_count\": 1, \"neg_count\": 0} <br> *Group_ids: art.2",
            "value": 1
        },
        {
            "color": "#ff7800",
            "group": "article",
            "id": "meet~art.4~~0x59b689b8",
            "label": "meet",
            "title": "*Freq: 1 <br> *Sen_Score: 0.0 <br> *Sentiment: {\"pos_count\": 0, \"neu_count\": 1, \"neg_count\": 0} <br> *Group_ids: art.4",
            "value": 1
        }
    ],
    "options": {
        "build_option": {
            "build_mode": 1,
            "n_thread": 5,
            "sentiment_ana_mode": "global",
            "use_thread_structure": false
        },
        "pruning_option": {
            "black_node_labels": [
                "wa",
                "a",
                "about",
                "above",
                "across",
                "after",
                "afterwards",
                "again",
                "against",
                "all",
                "almost",
                "alone",
                "along",
                "already",
                "also",
                "although",
                "always",
                "am",
                "among",
                "amongst",
                "amoungst",
                "an",
                "and",
                "another",
                "any",
                "anyhow",
                "anyone",
                "anything",
                "anyway",
                "anywhere",
                "are",
                "around",
                "as",
                "at",
                "be",
                "became",
                "because",
                "been",
                "before",
                "beforehand",
                "behind",
                "being",
                "below",
                "beside",
                "besides",
                "between",
                "beyond",
                "both",
                "but",
                "by",
                "can",
                "cannot",
                "could",
                "dare",
                "despite",
                "did",
                "do",
                "does",
                "done",
                "down",
                "during",
                "each",
                "eg",
                "either",
                "else",
                "elsewhere",
                "enough",
                "etc",
                "even",
                "ever",
                "every",
                "everyone",
                "everything",
                "everywhere",
                "except",
                "few",
                "first",
                "for",
                "former",
                "formerly",
                "from",
                "further",
                "furthermore",
                "had",
                "has",
                "have",
                "he",
                "hence",
                "her",
                "here",
                "hereabouts",
                "hereafter",
                "hereby",
                "herein",
                "hereinafter",
                "heretofore",
                "hereunder",
                "hereupon",
                "herewith",
                "hers",
                "herself",
                "him",
                "himself",
                "his",
                "how",
                "however",
                "i",
                "ie",
                "if",
                "in",
                "indeed",
                "inside",
                "instead",
                "into",
                "is",
                "it",
                "its",
                "itself",
                "last",
                "latter",
                "latterly",
                "least",
                "less",
                "lot",
                "lots",
                "many",
                "may",
                "me",
                "meanwhile",
                "might",
                "mine",
                "more",
                "moreover",
                "most",
                "mostly",
                "much",
                "must",
                "my",
                "myself",
                "namely",
                "near",
                "need",
                "neither",
                "never",
                "nevertheless",
                "next",
                "no",
                "nobody",
                "none",
                "noone",
                "nor",
                "not",
                "nothing",
                "now",
                "nowhere",
                "of",
                "off",
                "often",
                "oftentimes",
                "on",
                "once",
                "one",
                "only",
                "onto",
                "or",
                "other",
                "others",
                "otherwise",
                "ought",
                "our",
                "ours",
                "ourselves",
                "out",
                "outside",
                "over",
                "per",
                "perhaps",
                "rather",
                "re",
                "same",
                "second",
                "several",
                "shall",
                "she",
                "should",
                "since",
                "so",
                "some",
                "somehow",
                "someone",
                "something",
                "sometime",
                "sometimes",
                "somewhat",
                "somewhere",
                "still",
                "such",
                "than",
                "that",
                "the",
                "their",
                "theirs",
                "them",
                "themselves",
                "then",
                "thence",
                "there",
                "thereabouts",
                "thereafter",
                "thereby",
                "therefore",
                "therein",
                "thereof",
                "thereon",
                "thereupon",
                "these",
                "they",
                "third",
                "this",
                "those",
                "though",
                "through",
                "throughout",
                "thru",
                "thus",
                "to",
                "together",
                "too",
                "top",
                "toward",
                "towards",
                "under",
                "until",
                "up",
                "upon",
                "us",
                "used",
                "very",
                "via",
                "was",
                "we",
                "well",
                "were",
                "what",
                "whatever",
                "when",
                "whence",
                "whenever",
                "where",
                "whereafter",
                "whereas",
                "whereby",
                "wherein",
                "whereupon",
                "wherever",
                "whether",
                "which",
                "while",
                "whither",
                "who",
                "whoever",
                "whole",
                "whom",
                "whose",
                "why",
                "whyever",
                "will",
                "with",
                "within",
                "without",
                "would",
                "yes",
                "yet",
                "you",
                "your",
                "yours",
                "yourself",
                "yourselves"
            ],
            "edge_freq_min": 1,
            "enable_prunning": false,
            "min_word_length": 2,
            "node_degree_min": 2,
            "node_freq_min": 2,
            "regex_pattern": "[a-z\\/]+[-_]?",
            "remove_isolated_node": true,
            "white_node_labels": []
        },
        "timestamp": "2017-09-11 15:03:53 "
    }
}